{
    "version": "v6",
    "resultCount": 383,
    "queryArea": 34015.71734549517,
    "buildinfo": {
        "commit": "702904eefb44e1661a87af89cbef4130a4d86809",
        "commit_author": "bartvbl",
        "commit_date": "2021-02-24 17:00:03 +0100"
    },
    "results": [
        {
            "name": "T62.dat",
            "score": 14643376.357012272,
            "imageID": 0,
            "executionTimeSeconds": 6.585999965667725
        }, {
            "name": "T96.dat",
            "score": 129893901.14926147,
            "imageID": 0,
            "executionTimeSeconds": 6.572000026702881
        }, {
            "name": "T4.dat",
            "score": 130109507.72402191,
            "imageID": 0,
            "executionTimeSeconds": 6.627999782562256
        }, {
            "name": "T145.dat",
            "score": 138365145.42027283,
            "imageID": 0,
            "executionTimeSeconds": 6.557000160217285
        }, {
            "name": "T112.dat",
            "score": 139703688.3993988,
            "imageID": 0,
            "executionTimeSeconds": 6.567999839782715
        }, {
            "name": "T248.dat",
            "score": 140222208.68296814,
            "imageID": 0,
            "executionTimeSeconds": 1.659000039100647
        }, {
            "name": "T131.dat",
            "score": 141417285.3139572,
            "imageID": 0,
            "executionTimeSeconds": 1.649999976158142
        }, {
            "name": "T179.dat",
            "score": 143309678.90603638,
            "imageID": 0,
            "executionTimeSeconds": 1.6519999504089355
        }, {
            "name": "T3.dat",
            "score": 144470806.92095184,
            "imageID": 0,
            "executionTimeSeconds": 1.6610000133514404
        }, {
            "name": "T1.dat",
            "score": 145770715.59502983,
            "imageID": 0,
            "executionTimeSeconds": 1.6519999504089355
        }, 
        {
            "name": "T228.dat",
            "score": 146305868.89330292,
            "imageID": 0,
            "executionTimeSeconds": 1.6610000133514404
        }, {
            "name": "T51.dat",
            "score": 147654439.8764534,
            "imageID": 0,
            "executionTimeSeconds": 6.571000099182129
        }, {
            "name": "T262.dat",
            "score": 148216562.12152863,
            "imageID": 0,
            "executionTimeSeconds": 1.6610000133514404
        }, {
            "name": "T210.dat",
            "score": 148763255.5659008,
            "imageID": 0,
            "executionTimeSeconds": 1.6610000133514404
        }, {
            "name": "T12.dat",
            "score": 149420472.2516861,
            "imageID": 0,
            "executionTimeSeconds": 1.6579999923706055
        }, {
            "name": "T203.dat",
            "score": 149937680.229702,
            "imageID": 0,
            "executionTimeSeconds": 1.6660000085830688
        }, {
            "name": "T287.dat",
            "score": 150571588.52857208,
            "imageID": 0,
            "executionTimeSeconds": 1.656000018119812
        }, {
            "name": "T75.dat",
            "score": 150604960.50982666,
            "imageID": 0,
            "executionTimeSeconds": 6.626999855041504
        }, {
            "name": "T80.dat",
            "score": 151100761.08885574,
            "imageID": 0,
            "executionTimeSeconds": 1.6690000295639038
        }, {
            "name": "T60.dat",
            "score": 151182567.55514526,
            "imageID": 0,
            "executionTimeSeconds": 6.631999969482422
        }, 
        {
            "name": "T58.dat",
            "score": 151604643.79878998,
            "imageID": 0,
            "executionTimeSeconds": 6.572000026702881
        }, {
            "name": "T138.dat",
            "score": 151635872.26932526,
            "imageID": 0,
            "executionTimeSeconds": 1.649999976158142
        }, {
            "name": "T144.dat",
            "score": 152066266.42990494,
            "imageID": 0,
            "executionTimeSeconds": 6.558000087738037
        }, {
            "name": "T319.dat",
            "score": 152498891.23064423,
            "imageID": 0,
            "executionTimeSeconds": 1.659000039100647
        }, {
            "name": "T318.dat",
            "score": 153209629.1128273,
            "imageID": 0,
            "executionTimeSeconds": 1.6579999923706055
        }, {
            "name": "T124.dat",
            "score": 153627835.41500092,
            "imageID": 0,
            "executionTimeSeconds": 1.6729999780654907
        }, {
            "name": "T191.dat",
            "score": 153949805.9631195,
            "imageID": 0,
            "executionTimeSeconds": 1.6629999876022339
        }, {
            "name": "T360.dat",
            "score": 154466995.1210556,
            "imageID": 0,
            "executionTimeSeconds": 1.656999945640564
        }, {
            "name": "T149.dat",
            "score": 154603257.11882782,
            "imageID": 0,
            "executionTimeSeconds": 6.697000026702881
        }, {
            "name": "T34.dat",
            "score": 155122790.52700043,
            "imageID": 0,
            "executionTimeSeconds": 1.6490000486373901
        }, 
        {
            "name": "T59.dat",
            "score": 155165433.71181488,
            "imageID": 0,
            "executionTimeSeconds": 6.570000171661377
        }, {
            "name": "T283.dat",
            "score": 155254533.67561722,
            "imageID": 0,
            "executionTimeSeconds": 1.659000039100647
        }, {
            "name": "T13.dat",
            "score": 155267824.7668724,
            "imageID": 0,
            "executionTimeSeconds": 6.576000213623047
        }, {
            "name": "T249.dat",
            "score": 155351812.91711807,
            "imageID": 0,
            "executionTimeSeconds": 1.659000039100647
        }, {
            "name": "T354.dat",
            "score": 155475596.6120453,
            "imageID": 0,
            "executionTimeSeconds": 1.6610000133514404
        }, {
            "name": "T372.dat",
            "score": 155634222.39874268,
            "imageID": 0,
            "executionTimeSeconds": 1.659999966621399
        }, {
            "name": "T77.dat",
            "score": 155794370.68185806,
            "imageID": 0,
            "executionTimeSeconds": 1.6440000534057617
        }, {
            "name": "T5.dat",
            "score": 155797411.4055786,
            "imageID": 0,
            "executionTimeSeconds": 1.6640000343322754
        }, {
            "name": "T218.dat",
            "score": 155816831.60957718,
            "imageID": 0,
            "executionTimeSeconds": 1.6690000295639038
        }, {
            "name": "T256.dat",
            "score": 156147489.49588013,
            "imageID": 0,
            "executionTimeSeconds": 1.6540000438690186
        }, 
        {
            "name": "T304.dat",
            "score": 157689722.8109703,
            "imageID": 0,
            "executionTimeSeconds": 1.6629999876022339
        }, {
            "name": "T358.dat",
            "score": 157983259.4126358,
            "imageID": 0,
            "executionTimeSeconds": 1.6690000295639038
        }, {
            "name": "T104.dat",
            "score": 158032687.94612122,
            "imageID": 0,
            "executionTimeSeconds": 1.6690000295639038
        }, {
            "name": "T137.dat",
            "score": 158274765.62681198,
            "imageID": 0,
            "executionTimeSeconds": 1.6660000085830688
        }, {
            "name": "T53.dat",
            "score": 158446658.7504654,
            "imageID": 0,
            "executionTimeSeconds": 6.664999961853027
        }, {
            "name": "T122.dat",
            "score": 158480905.17974472,
            "imageID": 0,
            "executionTimeSeconds": 1.6480000019073486
        }, {
            "name": "T305.dat",
            "score": 158890645.36965942,
            "imageID": 0,
            "executionTimeSeconds": 1.659999966621399
        }, {
            "name": "T289.dat",
            "score": 158895706.707798,
            "imageID": 0,
            "executionTimeSeconds": 1.6619999408721924
        }, {
            "name": "T170.dat",
            "score": 159098765.30719757,
            "imageID": 0,
            "executionTimeSeconds": 1.6690000295639038
        }, {
            "name": "T155.dat",
            "score": 159178664.56487274,
            "imageID": 0,
            "executionTimeSeconds": 1.6660000085830688
        }, 
        {
            "name": "T308.dat",
            "score": 159689108.24600983,
            "imageID": 0,
            "executionTimeSeconds": 1.659999966621399
        }, {
            "name": "T108.dat",
            "score": 159917676.12369537,
            "imageID": 0,
            "executionTimeSeconds": 6.730999946594238
        }, {
            "name": "T21.dat",
            "score": 159992335.40642548,
            "imageID": 0,
            "executionTimeSeconds": 1.6649999618530273
        }, {
            "name": "T29.dat",
            "score": 160120934.59669113,
            "imageID": 0,
            "executionTimeSeconds": 1.6699999570846558
        }, {
            "name": "T111.dat",
            "score": 160271188.6199684,
            "imageID": 0,
            "executionTimeSeconds": 1.6679999828338623
        }, {
            "name": "T238.dat",
            "score": 160513732.08287048,
            "imageID": 0,
            "executionTimeSeconds": 1.6660000085830688
        }, {
            "name": "T136.dat",
            "score": 160601109.266037,
            "imageID": 0,
            "executionTimeSeconds": 1.6579999923706055
        }, {
            "name": "T197.dat",
            "score": 160803742.00504684,
            "imageID": 0,
            "executionTimeSeconds": 6.598999977111816
        }, {
            "name": "T171.dat",
            "score": 160927885.8506012,
            "imageID": 0,
            "executionTimeSeconds": 1.659999966621399
        }, {
            "name": "T310.dat",
            "score": 161231927.81516266,
            "imageID": 0,
            "executionTimeSeconds": 1.6619999408721924
        }, 
        {
            "name": "T362.dat",
            "score": 161231927.81516266,
            "imageID": 0,
            "executionTimeSeconds": 1.656999945640564
        }, {
            "name": "T225.dat",
            "score": 161248936.56801987,
            "imageID": 0,
            "executionTimeSeconds": 1.659999966621399
        }, {
            "name": "T366.dat",
            "score": 161277492.03224945,
            "imageID": 0,
            "executionTimeSeconds": 1.6619999408721924
        }, {
            "name": "T78.dat",
            "score": 161287354.65628433,
            "imageID": 0,
            "executionTimeSeconds": 1.659000039100647
        }, {
            "name": "T254.dat",
            "score": 161651542.8758049,
            "imageID": 0,
            "executionTimeSeconds": 1.659000039100647
        }, {
            "name": "T273.dat",
            "score": 161730820.3535576,
            "imageID": 0,
            "executionTimeSeconds": 1.6660000085830688
        }, {
            "name": "T264.dat",
            "score": 161867465.9344864,
            "imageID": 0,
            "executionTimeSeconds": 1.6670000553131104
        }, {
            "name": "T192.dat",
            "score": 162088766.60539246,
            "imageID": 0,
            "executionTimeSeconds": 6.581999778747559
        }, {
            "name": "T168.dat",
            "score": 162178739.92308426,
            "imageID": 0,
            "executionTimeSeconds": 1.656000018119812
        }, {
            "name": "T85.dat",
            "score": 162233155.06169128,
            "imageID": 0,
            "executionTimeSeconds": 1.6710000038146973
        }, 
        {
            "name": "T114.dat",
            "score": 162450048.93119812,
            "imageID": 0,
            "executionTimeSeconds": 1.6670000553131104
        }, {
            "name": "T126.dat",
            "score": 162468282.1012802,
            "imageID": 0,
            "executionTimeSeconds": 1.6640000343322754
        }, {
            "name": "T20.dat",
            "score": 163006449.04737854,
            "imageID": 0,
            "executionTimeSeconds": 1.6640000343322754
        }, {
            "name": "T174.dat",
            "score": 163405224.27773285,
            "imageID": 0,
            "executionTimeSeconds": 1.6579999923706055
        }, {
            "name": "T211.dat",
            "score": 163602561.2107849,
            "imageID": 0,
            "executionTimeSeconds": 1.6679999828338623
        }, {
            "name": "T247.dat",
            "score": 163830940.27228546,
            "imageID": 0,
            "executionTimeSeconds": 1.6649999618530273
        }, {
            "name": "T26.dat",
            "score": 164387664.93493652,
            "imageID": 0,
            "executionTimeSeconds": 1.6610000133514404
        }, {
            "name": "T371.dat",
            "score": 164496215.18278503,
            "imageID": 0,
            "executionTimeSeconds": 1.6549999713897705
        }, {
            "name": "T201.dat",
            "score": 164501695.25858688,
            "imageID": 0,
            "executionTimeSeconds": 1.6649999618530273
        }, {
            "name": "T9.dat",
            "score": 164639037.75877762,
            "imageID": 0,
            "executionTimeSeconds": 1.6629999876022339
        }, 
        {
            "name": "T268.dat",
            "score": 164645542.45490265,
            "imageID": 0,
            "executionTimeSeconds": 1.6610000133514404
        }, {
            "name": "T95.dat",
            "score": 164702856.48955917,
            "imageID": 0,
            "executionTimeSeconds": 1.6519999504089355
        }, {
            "name": "T207.dat",
            "score": 164799563.1123047,
            "imageID": 0,
            "executionTimeSeconds": 1.6649999618530273
        }, {
            "name": "T219.dat",
            "score": 164985195.94773102,
            "imageID": 0,
            "executionTimeSeconds": 1.6820000410079956
        }, {
            "name": "T31.dat",
            "score": 165094155.46635818,
            "imageID": 0,
            "executionTimeSeconds": 1.6579999923706055
        }, {
            "name": "T334.dat",
            "score": 165215484.51831627,
            "imageID": 0,
            "executionTimeSeconds": 1.6670000553131104
        }, {
            "name": "T99.dat",
            "score": 165287546.25853348,
            "imageID": 0,
            "executionTimeSeconds": 1.6699999570846558
        }, {
            "name": "T327.dat",
            "score": 165569446.60446167,
            "imageID": 0,
            "executionTimeSeconds": 1.6510000228881836
        }, {
            "name": "T326.dat",
            "score": 165848566.0225582,
            "imageID": 0,
            "executionTimeSeconds": 1.6519999504089355
        }, {
            "name": "T128.dat",
            "score": 165898229.10876846,
            "imageID": 0,
            "executionTimeSeconds": 1.6619999408721924
        }, 
        {
            "name": "T164.dat",
            "score": 166353119.07044983,
            "imageID": 0,
            "executionTimeSeconds": 1.6629999876022339
        }, {
            "name": "T183.dat",
            "score": 166851077.00709915,
            "imageID": 0,
            "executionTimeSeconds": 1.659000039100647
        }, {
            "name": "T258.dat",
            "score": 167221966.4502678,
            "imageID": 0,
            "executionTimeSeconds": 1.6640000343322754
        }, {
            "name": "T154.dat",
            "score": 167446125.05269623,
            "imageID": 0,
            "executionTimeSeconds": 1.6699999570846558
        }, {
            "name": "T48.dat",
            "score": 167537688.31373215,
            "imageID": 0,
            "executionTimeSeconds": 1.656999945640564
        }, {
            "name": "T176.dat",
            "score": 167615173.55693436,
            "imageID": 0,
            "executionTimeSeconds": 1.6579999923706055
        }, {
            "name": "T163.dat",
            "score": 167775659.5401268,
            "imageID": 0,
            "executionTimeSeconds": 1.6610000133514404
        }, {
            "name": "T54.dat",
            "score": 167910103.8341217,
            "imageID": 0,
            "executionTimeSeconds": 6.568999767303467
        }, {
            "name": "T267.dat",
            "score": 167943855.86797333,
            "imageID": 0,
            "executionTimeSeconds": 1.6729999780654907
        }, {
            "name": "T125.dat",
            "score": 167998173.8898239,
            "imageID": 0,
            "executionTimeSeconds": 1.656999945640564
        }, 
        {
            "name": "T139.dat",
            "score": 168166695.73486328,
            "imageID": 0,
            "executionTimeSeconds": 1.6519999504089355
        }, {
            "name": "T236.dat",
            "score": 168233427.0556183,
            "imageID": 0,
            "executionTimeSeconds": 1.6640000343322754
        }, {
            "name": "T223.dat",
            "score": 168272197.2314148,
            "imageID": 0,
            "executionTimeSeconds": 1.6649999618530273
        }, {
            "name": "T117.dat",
            "score": 168621309.08605576,
            "imageID": 0,
            "executionTimeSeconds": 1.6759999990463257
        }, {
            "name": "T177.dat",
            "score": 168644945.9522171,
            "imageID": 0,
            "executionTimeSeconds": 1.659999966621399
        }, {
            "name": "T329.dat",
            "score": 168723840.48744583,
            "imageID": 0,
            "executionTimeSeconds": 1.6619999408721924
        }, {
            "name": "T147.dat",
            "score": 169194185.49839783,
            "imageID": 0,
            "executionTimeSeconds": 1.6519999504089355
        }, {
            "name": "T343.dat",
            "score": 169474921.0933075,
            "imageID": 0,
            "executionTimeSeconds": 1.6579999923706055
        }, {
            "name": "T25.dat",
            "score": 169517141.8182106,
            "imageID": 0,
            "executionTimeSeconds": 1.656999945640564
        }, {
            "name": "T157.dat",
            "score": 169721907.6137085,
            "imageID": 0,
            "executionTimeSeconds": 1.652999997138977
        }, 
        {
            "name": "T344.dat",
            "score": 169783279.65836716,
            "imageID": 0,
            "executionTimeSeconds": 1.6610000133514404
        }, {
            "name": "T178.dat",
            "score": 169918497.9358673,
            "imageID": 0,
            "executionTimeSeconds": 1.6690000295639038
        }, {
            "name": "T330.dat",
            "score": 170030554.8605194,
            "imageID": 0,
            "executionTimeSeconds": 6.577000141143799
        }, {
            "name": "T279.dat",
            "score": 170175393.2931404,
            "imageID": 0,
            "executionTimeSeconds": 1.6679999828338623
        }, {
            "name": "T88.dat",
            "score": 170214753.29822922,
            "imageID": 0,
            "executionTimeSeconds": 1.6670000553131104
        }, {
            "name": "T186.dat",
            "score": 170244070.4956627,
            "imageID": 0,
            "executionTimeSeconds": 1.6579999923706055
        }, {
            "name": "T151.dat",
            "score": 170292858.4287796,
            "imageID": 0,
            "executionTimeSeconds": 1.6640000343322754
        }, {
            "name": "T103.dat",
            "score": 170564918.41884232,
            "imageID": 0,
            "executionTimeSeconds": 1.6670000553131104
        }, {
            "name": "T277.dat",
            "score": 170607311.43494797,
            "imageID": 0,
            "executionTimeSeconds": 1.6679999828338623
        }, {
            "name": "T230.dat",
            "score": 170721438.66722107,
            "imageID": 0,
            "executionTimeSeconds": 1.659000039100647
        }, 
        {
            "name": "T281.dat",
            "score": 170807067.35945892,
            "imageID": 0,
            "executionTimeSeconds": 1.652999997138977
        }, {
            "name": "T222.dat",
            "score": 170984368.3905716,
            "imageID": 0,
            "executionTimeSeconds": 1.6510000228881836
        }, {
            "name": "T288.dat",
            "score": 170999836.308712,
            "imageID": 0,
            "executionTimeSeconds": 1.6740000247955322
        }, {
            "name": "T123.dat",
            "score": 171123276.520607,
            "imageID": 0,
            "executionTimeSeconds": 1.6610000133514404
        }, {
            "name": "T94.dat",
            "score": 171637210.7157402,
            "imageID": 0,
            "executionTimeSeconds": 1.656999945640564
        }, {
            "name": "T143.dat",
            "score": 171653857.23815536,
            "imageID": 0,
            "executionTimeSeconds": 1.6729999780654907
        }, {
            "name": "T313.dat",
            "score": 171659209.8944702,
            "imageID": 0,
            "executionTimeSeconds": 1.652999997138977
        }, {
            "name": "T87.dat",
            "score": 171731160.4219513,
            "imageID": 0,
            "executionTimeSeconds": 1.659999966621399
        }, {
            "name": "T182.dat",
            "score": 171820486.4913826,
            "imageID": 0,
            "executionTimeSeconds": 1.6549999713897705
        }, {
            "name": "T57.dat",
            "score": 171948151.99101257,
            "imageID": 0,
            "executionTimeSeconds": 1.6679999828338623
        }, 
        {
            "name": "T107.dat",
            "score": 172296748.12779236,
            "imageID": 0,
            "executionTimeSeconds": 1.6660000085830688
        }, {
            "name": "T341.dat",
            "score": 172314818.9021988,
            "imageID": 0,
            "executionTimeSeconds": 1.6649999618530273
        }, {
            "name": "T70.dat",
            "score": 172318702.39292908,
            "imageID": 0,
            "executionTimeSeconds": 1.6540000438690186
        }, {
            "name": "T217.dat",
            "score": 172509546.3080597,
            "imageID": 0,
            "executionTimeSeconds": 1.652999997138977
        }, {
            "name": "T27.dat",
            "score": 172629689.24762344,
            "imageID": 0,
            "executionTimeSeconds": 1.6640000343322754
        }, {
            "name": "T47.dat",
            "score": 172677150.75488663,
            "imageID": 0,
            "executionTimeSeconds": 1.6549999713897705
        }, {
            "name": "T376.dat",
            "score": 172805748.73845673,
            "imageID": 0,
            "executionTimeSeconds": 1.6670000553131104
        }, {
            "name": "T175.dat",
            "score": 172852038.05344772,
            "imageID": 0,
            "executionTimeSeconds": 6.622000217437744
        }, {
            "name": "T15.dat",
            "score": 172865414.13357162,
            "imageID": 0,
            "executionTimeSeconds": 1.656000018119812
        }, {
            "name": "T86.dat",
            "score": 173067215.8089943,
            "imageID": 0,
            "executionTimeSeconds": 6.554999828338623
        }, 
        {
            "name": "T8.dat",
            "score": 173235484.21764374,
            "imageID": 0,
            "executionTimeSeconds": 1.6670000553131104
        }, {
            "name": "T242.dat",
            "score": 173628379.39466476,
            "imageID": 0,
            "executionTimeSeconds": 1.6640000343322754
        }, {
            "name": "T291.dat",
            "score": 173672744.23276138,
            "imageID": 0,
            "executionTimeSeconds": 1.6640000343322754
        }, {
            "name": "T199.dat",
            "score": 173804810.73023987,
            "imageID": 0,
            "executionTimeSeconds": 1.656999945640564
        }, {
            "name": "T216.dat",
            "score": 173849291.38755798,
            "imageID": 0,
            "executionTimeSeconds": 1.6540000438690186
        }, {
            "name": "T30.dat",
            "score": 173949294.72932434,
            "imageID": 0,
            "executionTimeSeconds": 1.6549999713897705
        }, {
            "name": "T79.dat",
            "score": 174089629.75642014,
            "imageID": 0,
            "executionTimeSeconds": 1.6640000343322754
        }, {
            "name": "T148.dat",
            "score": 174141067.1803627,
            "imageID": 0,
            "executionTimeSeconds": 6.561999797821045
        }, {
            "name": "T64.dat",
            "score": 174178990.73560333,
            "imageID": 0,
            "executionTimeSeconds": 1.6649999618530273
        }, {
            "name": "T215.dat",
            "score": 174214912.4040947,
            "imageID": 0,
            "executionTimeSeconds": 1.656000018119812
        }, 
        {
            "name": "T227.dat",
            "score": 174236258.58129883,
            "imageID": 0,
            "executionTimeSeconds": 1.6679999828338623
        }, {
            "name": "T36.dat",
            "score": 174240639.9276619,
            "imageID": 0,
            "executionTimeSeconds": 1.656999945640564
        }, {
            "name": "T187.dat",
            "score": 174541939.7246666,
            "imageID": 0,
            "executionTimeSeconds": 1.6690000295639038
        }, {
            "name": "T169.dat",
            "score": 174571648.55213547,
            "imageID": 0,
            "executionTimeSeconds": 1.649999976158142
        }, {
            "name": "T355.dat",
            "score": 174810247.29799652,
            "imageID": 0,
            "executionTimeSeconds": 1.659999966621399
        }, {
            "name": "T153.dat",
            "score": 174835460.96159363,
            "imageID": 0,
            "executionTimeSeconds": 1.6549999713897705
        }, {
            "name": "T172.dat",
            "score": 174836808.2250862,
            "imageID": 0,
            "executionTimeSeconds": 1.649999976158142
        }, {
            "name": "T253.dat",
            "score": 174912215.54613495,
            "imageID": 0,
            "executionTimeSeconds": 6.610000133514404
        }, {
            "name": "T101.dat",
            "score": 175084459.0425129,
            "imageID": 0,
            "executionTimeSeconds": 6.559999942779541
        }, {
            "name": "T240.dat",
            "score": 175219241.758461,
            "imageID": 0,
            "executionTimeSeconds": 1.6679999828338623
        }, 
        {
            "name": "T46.dat",
            "score": 175240008.44535065,
            "imageID": 0,
            "executionTimeSeconds": 1.659999966621399
        }, {
            "name": "T231.dat",
            "score": 175380780.73705673,
            "imageID": 0,
            "executionTimeSeconds": 1.656000018119812
        }, {
            "name": "T110.dat",
            "score": 175655691.99147034,
            "imageID": 0,
            "executionTimeSeconds": 6.579999923706055
        }, {
            "name": "T129.dat",
            "score": 175924944.16322708,
            "imageID": 0,
            "executionTimeSeconds": 1.6490000486373901
        }, {
            "name": "T102.dat",
            "score": 176114799.41918182,
            "imageID": 0,
            "executionTimeSeconds": 1.659999966621399
        }, {
            "name": "T320.dat",
            "score": 176155483.30061722,
            "imageID": 0,
            "executionTimeSeconds": 6.566999912261963
        }, {
            "name": "T212.dat",
            "score": 176223309.90539932,
            "imageID": 0,
            "executionTimeSeconds": 1.6519999504089355
        }, {
            "name": "T115.dat",
            "score": 176356341.1824417,
            "imageID": 0,
            "executionTimeSeconds": 1.6670000553131104
        }, {
            "name": "T269.dat",
            "score": 176430915.5992546,
            "imageID": 0,
            "executionTimeSeconds": 1.6610000133514404
        }, {
            "name": "T193.dat",
            "score": 176434224.87169266,
            "imageID": 0,
            "executionTimeSeconds": 1.6549999713897705
        }, 
        {
            "name": "T257.dat",
            "score": 176517036.27085876,
            "imageID": 0,
            "executionTimeSeconds": 1.6519999504089355
        }, {
            "name": "T312.dat",
            "score": 176555534.01263046,
            "imageID": 0,
            "executionTimeSeconds": 1.6740000247955322
        }, {
            "name": "T127.dat",
            "score": 176643146.66376114,
            "imageID": 0,
            "executionTimeSeconds": 1.659999966621399
        }, {
            "name": "T347.dat",
            "score": 176745908.50141144,
            "imageID": 0,
            "executionTimeSeconds": 1.6679999828338623
        }, {
            "name": "T91.dat",
            "score": 177057893.24180603,
            "imageID": 0,
            "executionTimeSeconds": 1.6480000019073486
        }, {
            "name": "T261.dat",
            "score": 177180230.8521347,
            "imageID": 0,
            "executionTimeSeconds": 1.690999984741211
        }, {
            "name": "T339.dat",
            "score": 177371470.53604507,
            "imageID": 0,
            "executionTimeSeconds": 1.6720000505447388
        }, {
            "name": "T208.dat",
            "score": 177425861.12433243,
            "imageID": 0,
            "executionTimeSeconds": 1.659999966621399
        }, {
            "name": "T166.dat",
            "score": 177528322.1227684,
            "imageID": 0,
            "executionTimeSeconds": 1.6549999713897705
        }, {
            "name": "T66.dat",
            "score": 177965810.51527405,
            "imageID": 0,
            "executionTimeSeconds": 1.656000018119812
        }, 
        {
            "name": "T233.dat",
            "score": 178022912.40447235,
            "imageID": 0,
            "executionTimeSeconds": 1.6660000085830688
        }, {
            "name": "T357.dat",
            "score": 178302711.81098938,
            "imageID": 0,
            "executionTimeSeconds": 1.6579999923706055
        }, {
            "name": "T68.dat",
            "score": 178368176.8657608,
            "imageID": 0,
            "executionTimeSeconds": 1.656999945640564
        }, {
            "name": "T331.dat",
            "score": 178423608.33556366,
            "imageID": 0,
            "executionTimeSeconds": 1.659000039100647
        }, {
            "name": "T100.dat",
            "score": 178718394.7190361,
            "imageID": 0,
            "executionTimeSeconds": 1.6540000438690186
        }, {
            "name": "T83.dat",
            "score": 178826727.78172302,
            "imageID": 0,
            "executionTimeSeconds": 1.6699999570846558
        }, {
            "name": "T11.dat",
            "score": 179014003.78813553,
            "imageID": 0,
            "executionTimeSeconds": 1.6690000295639038
        }, {
            "name": "T76.dat",
            "score": 179059844.5081482,
            "imageID": 0,
            "executionTimeSeconds": 1.649999976158142
        }, {
            "name": "T2.dat",
            "score": 179138934.43600464,
            "imageID": 0,
            "executionTimeSeconds": 1.6679999828338623
        }, {
            "name": "T159.dat",
            "score": 179290161.06391144,
            "imageID": 0,
            "executionTimeSeconds": 1.6640000343322754
        }, 
        {
            "name": "T234.dat",
            "score": 179520705.04877472,
            "imageID": 0,
            "executionTimeSeconds": 1.6490000486373901
        }, {
            "name": "T302.dat",
            "score": 179784020.6985016,
            "imageID": 0,
            "executionTimeSeconds": 1.684999942779541
        }, {
            "name": "T317.dat",
            "score": 180309707.0467186,
            "imageID": 0,
            "executionTimeSeconds": 1.659999966621399
        }, {
            "name": "T345.dat",
            "score": 180326380.34495544,
            "imageID": 0,
            "executionTimeSeconds": 1.6770000457763672
        }, {
            "name": "T146.dat",
            "score": 180363667.18684006,
            "imageID": 0,
            "executionTimeSeconds": 1.6480000019073486
        }, {
            "name": "T213.dat",
            "score": 180440639.47369766,
            "imageID": 0,
            "executionTimeSeconds": 1.6490000486373901
        }, {
            "name": "T303.dat",
            "score": 180463944.78523254,
            "imageID": 0,
            "executionTimeSeconds": 1.659000039100647
        }, {
            "name": "T298.dat",
            "score": 180649911.99092865,
            "imageID": 0,
            "executionTimeSeconds": 1.6629999876022339
        }, {
            "name": "T65.dat",
            "score": 180679557.19612885,
            "imageID": 0,
            "executionTimeSeconds": 1.6510000228881836
        }, {
            "name": "T160.dat",
            "score": 180800980.2738533,
            "imageID": 0,
            "executionTimeSeconds": 1.6430000066757202
        }, 
        {
            "name": "T338.dat",
            "score": 180850898.15231323,
            "imageID": 0,
            "executionTimeSeconds": 1.6640000343322754
        }, {
            "name": "T50.dat",
            "score": 180914959.36536026,
            "imageID": 0,
            "executionTimeSeconds": 6.566999912261963
        }, {
            "name": "T204.dat",
            "score": 180915511.35625076,
            "imageID": 0,
            "executionTimeSeconds": 1.659000039100647
        }, {
            "name": "T69.dat",
            "score": 180935993.46720123,
            "imageID": 0,
            "executionTimeSeconds": 1.659999966621399
        }, {
            "name": "T81.dat",
            "score": 181112430.7320366,
            "imageID": 0,
            "executionTimeSeconds": 1.6649999618530273
        }, {
            "name": "T325.dat",
            "score": 181312180.59137726,
            "imageID": 0,
            "executionTimeSeconds": 1.6519999504089355
        }, {
            "name": "T116.dat",
            "score": 181538178.4513092,
            "imageID": 0,
            "executionTimeSeconds": 6.716000080108643
        }, {
            "name": "T226.dat",
            "score": 181643290.85114288,
            "imageID": 0,
            "executionTimeSeconds": 1.6540000438690186
        }, {
            "name": "T161.dat",
            "score": 181713321.36259842,
            "imageID": 0,
            "executionTimeSeconds": 1.649999976158142
        }, {
            "name": "T349.dat",
            "score": 181779341.8824196,
            "imageID": 0,
            "executionTimeSeconds": 1.6759999990463257
        }, 
        {
            "name": "T292.dat",
            "score": 181849428.9393463,
            "imageID": 0,
            "executionTimeSeconds": 1.659999966621399
        }, {
            "name": "T142.dat",
            "score": 181867154.10630798,
            "imageID": 0,
            "executionTimeSeconds": 1.6519999504089355
        }, {
            "name": "T241.dat",
            "score": 182103922.45650482,
            "imageID": 0,
            "executionTimeSeconds": 1.659000039100647
        }, {
            "name": "T84.dat",
            "score": 182198322.85520554,
            "imageID": 0,
            "executionTimeSeconds": 1.6610000133514404
        }, {
            "name": "T16.dat",
            "score": 182256394.4548378,
            "imageID": 0,
            "executionTimeSeconds": 1.6449999809265137
        }, {
            "name": "T282.dat",
            "score": 182404147.8736801,
            "imageID": 0,
            "executionTimeSeconds": 1.6629999876022339
        }, {
            "name": "T55.dat",
            "score": 182405850.51394844,
            "imageID": 0,
            "executionTimeSeconds": 6.63100004196167
        }, {
            "name": "T260.dat",
            "score": 183474956.22163773,
            "imageID": 0,
            "executionTimeSeconds": 1.6740000247955322
        }, {
            "name": "T61.dat",
            "score": 183772538.28053284,
            "imageID": 0,
            "executionTimeSeconds": 1.6740000247955322
        }, {
            "name": "T272.dat",
            "score": 183839076.82047272,
            "imageID": 0,
            "executionTimeSeconds": 6.5980000495910645
        }, 
        {
            "name": "T237.dat",
            "score": 184045774.5332451,
            "imageID": 0,
            "executionTimeSeconds": 1.6640000343322754
        }, {
            "name": "T73.dat",
            "score": 184210198.53647614,
            "imageID": 0,
            "executionTimeSeconds": 1.6640000343322754
        }, {
            "name": "T243.dat",
            "score": 184267903.87509155,
            "imageID": 0,
            "executionTimeSeconds": 1.687000036239624
        }, {
            "name": "T271.dat",
            "score": 184486058.83049393,
            "imageID": 0,
            "executionTimeSeconds": 1.6629999876022339
        }, {
            "name": "T365.dat",
            "score": 184542739.26341248,
            "imageID": 0,
            "executionTimeSeconds": 1.656999945640564
        }, {
            "name": "T92.dat",
            "score": 184549038.53907776,
            "imageID": 0,
            "executionTimeSeconds": 1.6610000133514404
        }, {
            "name": "T198.dat",
            "score": 184672195.77568054,
            "imageID": 0,
            "executionTimeSeconds": 1.6579999923706055
        }, {
            "name": "T286.dat",
            "score": 184681828.7623253,
            "imageID": 0,
            "executionTimeSeconds": 1.694000005722046
        }, {
            "name": "T316.dat",
            "score": 184843793.5881958,
            "imageID": 0,
            "executionTimeSeconds": 1.6629999876022339
        }, {
            "name": "T97.dat",
            "score": 184845353.82368088,
            "imageID": 0,
            "executionTimeSeconds": 1.6619999408721924
        }, 
        {
            "name": "T342.dat",
            "score": 184928738.74010468,
            "imageID": 0,
            "executionTimeSeconds": 1.6640000343322754
        }, {
            "name": "T165.dat",
            "score": 184936029.28818512,
            "imageID": 0,
            "executionTimeSeconds": 1.6549999713897705
        }, {
            "name": "T232.dat",
            "score": 185061423.1454239,
            "imageID": 0,
            "executionTimeSeconds": 1.6549999713897705
        }, {
            "name": "T35.dat",
            "score": 185286546.63705063,
            "imageID": 0,
            "executionTimeSeconds": 1.6610000133514404
        }, {
            "name": "T39.dat",
            "score": 185295576.84035492,
            "imageID": 0,
            "executionTimeSeconds": 1.6649999618530273
        }, {
            "name": "T209.dat",
            "score": 185347520.14801025,
            "imageID": 0,
            "executionTimeSeconds": 1.6729999780654907
        }, {
            "name": "T263.dat",
            "score": 185372824.2228012,
            "imageID": 0,
            "executionTimeSeconds": 1.6619999408721924
        }, {
            "name": "T56.dat",
            "score": 185698374.79930878,
            "imageID": 0,
            "executionTimeSeconds": 6.584000110626221
        }, {
            "name": "T307.dat",
            "score": 185851771.4965973,
            "imageID": 0,
            "executionTimeSeconds": 1.659999966621399
        }, {
            "name": "T181.dat",
            "score": 185976590.83007812,
            "imageID": 0,
            "executionTimeSeconds": 1.6579999923706055
        }, 
        {
            "name": "T184.dat",
            "score": 186003754.20197296,
            "imageID": 0,
            "executionTimeSeconds": 1.6690000295639038
        }, {
            "name": "T252.dat",
            "score": 186180381.07733154,
            "imageID": 0,
            "executionTimeSeconds": 1.6540000438690186
        }, {
            "name": "T162.dat",
            "score": 186285090.3225708,
            "imageID": 0,
            "executionTimeSeconds": 1.6540000438690186
        }, {
            "name": "T293.dat",
            "score": 186376039.9220085,
            "imageID": 0,
            "executionTimeSeconds": 1.6670000553131104
        }, {
            "name": "T6.dat",
            "score": 186452686.78373718,
            "imageID": 0,
            "executionTimeSeconds": 1.656000018119812
        }, {
            "name": "T276.dat",
            "score": 186486691.84556198,
            "imageID": 0,
            "executionTimeSeconds": 1.6549999713897705
        }, {
            "name": "T40.dat",
            "score": 186664839.4249878,
            "imageID": 0,
            "executionTimeSeconds": 1.6540000438690186
        }, {
            "name": "T14.dat",
            "score": 186883615.8266449,
            "imageID": 0,
            "executionTimeSeconds": 1.6619999408721924
        }, {
            "name": "T98.dat",
            "score": 186956318.6694374,
            "imageID": 0,
            "executionTimeSeconds": 1.6619999408721924
        }, {
            "name": "T290.dat",
            "score": 187066070.4589386,
            "imageID": 0,
            "executionTimeSeconds": 1.6480000019073486
        }, 
        {
            "name": "T314.dat",
            "score": 187337865.7075081,
            "imageID": 0,
            "executionTimeSeconds": 1.652999997138977
        }, {
            "name": "T195.dat",
            "score": 187446728.44407654,
            "imageID": 0,
            "executionTimeSeconds": 1.6619999408721924
        }, {
            "name": "T33.dat",
            "score": 187473115.79322815,
            "imageID": 0,
            "executionTimeSeconds": 1.652999997138977
        }, {
            "name": "T32.dat",
            "score": 187773992.06349182,
            "imageID": 0,
            "executionTimeSeconds": 1.659000039100647
        }, {
            "name": "T235.dat",
            "score": 188158694.1347351,
            "imageID": 0,
            "executionTimeSeconds": 1.6749999523162842
        }, {
            "name": "T180.dat",
            "score": 188264721.38893127,
            "imageID": 0,
            "executionTimeSeconds": 1.6720000505447388
        }, {
            "name": "T63.dat",
            "score": 188443932.5730133,
            "imageID": 0,
            "executionTimeSeconds": 1.6480000019073486
        }, {
            "name": "T309.dat",
            "score": 188785012.00095367,
            "imageID": 0,
            "executionTimeSeconds": 1.6629999876022339
        }, {
            "name": "T89.dat",
            "score": 188813786.5192337,
            "imageID": 0,
            "executionTimeSeconds": 1.6610000133514404
        }, {
            "name": "T190.dat",
            "score": 188956661.2957077,
            "imageID": 0,
            "executionTimeSeconds": 1.659000039100647
        }, 
        {
            "name": "T205.dat",
            "score": 189764147.41187286,
            "imageID": 0,
            "executionTimeSeconds": 1.6579999923706055
        }, {
            "name": "T220.dat",
            "score": 189780550.2926407,
            "imageID": 0,
            "executionTimeSeconds": 1.656000018119812
        }, {
            "name": "T167.dat",
            "score": 189892414.3064537,
            "imageID": 0,
            "executionTimeSeconds": 1.6549999713897705
        }, {
            "name": "T328.dat",
            "score": 190036660.43928528,
            "imageID": 0,
            "executionTimeSeconds": 1.656999945640564
        }, {
            "name": "T121.dat",
            "score": 190082549.01404572,
            "imageID": 0,
            "executionTimeSeconds": 1.6629999876022339
        }, {
            "name": "T246.dat",
            "score": 190377344.64908218,
            "imageID": 0,
            "executionTimeSeconds": 1.6660000085830688
        }, {
            "name": "T140.dat",
            "score": 190561765.74838257,
            "imageID": 0,
            "executionTimeSeconds": 1.659000039100647
        }, {
            "name": "T221.dat",
            "score": 190857429.14243317,
            "imageID": 0,
            "executionTimeSeconds": 1.659000039100647
        }, {
            "name": "T214.dat",
            "score": 190965080.35486603,
            "imageID": 0,
            "executionTimeSeconds": 1.649999976158142
        }, {
            "name": "T37.dat",
            "score": 190976266.12800598,
            "imageID": 0,
            "executionTimeSeconds": 6.578000068664551
        }, 
        {
            "name": "T90.dat",
            "score": 191502183.5207901,
            "imageID": 0,
            "executionTimeSeconds": 1.6549999713897705
        }, {
            "name": "T250.dat",
            "score": 191723465.6860962,
            "imageID": 0,
            "executionTimeSeconds": 6.586999893188477
        }, {
            "name": "T202.dat",
            "score": 192654324.66749573,
            "imageID": 0,
            "executionTimeSeconds": 1.6490000486373901
        }, {
            "name": "T224.dat",
            "score": 192660885.51937866,
            "imageID": 0,
            "executionTimeSeconds": 1.6419999599456787
        }, {
            "name": "T239.dat",
            "score": 192918591.58789444,
            "imageID": 0,
            "executionTimeSeconds": 6.5980000495910645
        }, {
            "name": "T106.dat",
            "score": 193026199.56814575,
            "imageID": 0,
            "executionTimeSeconds": 1.6610000133514404
        }, {
            "name": "T10.dat",
            "score": 193056203.7789917,
            "imageID": 0,
            "executionTimeSeconds": 1.6660000085830688
        }, {
            "name": "T194.dat",
            "score": 193491484.3074417,
            "imageID": 0,
            "executionTimeSeconds": 1.6510000228881836
        }, {
            "name": "T306.dat",
            "score": 193495813.57074738,
            "imageID": 0,
            "executionTimeSeconds": 1.6790000200271606
        }, {
            "name": "T134.dat",
            "score": 193528597.22667694,
            "imageID": 0,
            "executionTimeSeconds": 1.652999997138977
        }, 
        {
            "name": "T285.dat",
            "score": 193545917.55041504,
            "imageID": 0,
            "executionTimeSeconds": 6.567999839782715
        }, {
            "name": "T255.dat",
            "score": 193557806.29512024,
            "imageID": 0,
            "executionTimeSeconds": 1.6640000343322754
        }, {
            "name": "T119.dat",
            "score": 193559794.60780334,
            "imageID": 0,
            "executionTimeSeconds": 1.6610000133514404
        }, {
            "name": "T364.dat",
            "score": 193626772.53490067,
            "imageID": 0,
            "executionTimeSeconds": 1.652999997138977
        }, {
            "name": "T72.dat",
            "score": 193857705.2248764,
            "imageID": 0,
            "executionTimeSeconds": 1.6629999876022339
        }, {
            "name": "T38.dat",
            "score": 193947821.69462585,
            "imageID": 0,
            "executionTimeSeconds": 1.6579999923706055
        }, {
            "name": "T251.dat",
            "score": 193950238.29288483,
            "imageID": 0,
            "executionTimeSeconds": 1.6519999504089355
        }, {
            "name": "T270.dat",
            "score": 194132735.82685852,
            "imageID": 0,
            "executionTimeSeconds": 1.6679999828338623
        }, {
            "name": "T265.dat",
            "score": 194598128.79701233,
            "imageID": 0,
            "executionTimeSeconds": 1.656999945640564
        }, {
            "name": "T361.dat",
            "score": 194614842.13502502,
            "imageID": 0,
            "executionTimeSeconds": 1.6629999876022339
        }, 
        {
            "name": "T275.dat",
            "score": 194645366.7073593,
            "imageID": 0,
            "executionTimeSeconds": 1.6649999618530273
        }, {
            "name": "T105.dat",
            "score": 194657749.11105728,
            "imageID": 0,
            "executionTimeSeconds": 1.6699999570846558
        }, {
            "name": "T93.dat",
            "score": 195134530.0010643,
            "imageID": 0,
            "executionTimeSeconds": 1.6519999504089355
        }, {
            "name": "T152.dat",
            "score": 195272998.8513298,
            "imageID": 0,
            "executionTimeSeconds": 1.6660000085830688
        }, {
            "name": "T82.dat",
            "score": 196044468.77744293,
            "imageID": 0,
            "executionTimeSeconds": 1.656000018119812
        }, {
            "name": "T113.dat",
            "score": 196564828.4396248,
            "imageID": 0,
            "executionTimeSeconds": 1.659999966621399
        }, {
            "name": "T311.dat",
            "score": 196842903.59281158,
            "imageID": 0,
            "executionTimeSeconds": 1.6619999408721924
        }, {
            "name": "T370.dat",
            "score": 197038299.4739151,
            "imageID": 0,
            "executionTimeSeconds": 1.6610000133514404
        }, {
            "name": "T196.dat",
            "score": 197114170.69530106,
            "imageID": 0,
            "executionTimeSeconds": 1.652999997138977
        }, {
            "name": "T278.dat",
            "score": 197160381.7245102,
            "imageID": 0,
            "executionTimeSeconds": 1.6649999618530273
        }, 
        {
            "name": "T133.dat",
            "score": 197540406.48303986,
            "imageID": 0,
            "executionTimeSeconds": 1.6749999523162842
        }, {
            "name": "T324.dat",
            "score": 197540832.52057266,
            "imageID": 0,
            "executionTimeSeconds": 1.656999945640564
        }, {
            "name": "T274.dat",
            "score": 197670511.8677063,
            "imageID": 0,
            "executionTimeSeconds": 1.6759999990463257
        }, {
            "name": "T185.dat",
            "score": 198019990.80736542,
            "imageID": 0,
            "executionTimeSeconds": 3.2960000038146973
        }, {
            "name": "T71.dat",
            "score": 198709577.2485695,
            "imageID": 0,
            "executionTimeSeconds": 1.6540000438690186
        }, {
            "name": "T351.dat",
            "score": 199519420.40566254,
            "imageID": 0,
            "executionTimeSeconds": 1.6670000553131104
        }, {
            "name": "T245.dat",
            "score": 199695392.4808731,
            "imageID": 0,
            "executionTimeSeconds": 1.6670000553131104
        }, {
            "name": "T301.dat",
            "score": 199723440.14442444,
            "imageID": 0,
            "executionTimeSeconds": 1.6510000228881836
        }, {
            "name": "T42.dat",
            "score": 200429564.13567352,
            "imageID": 0,
            "executionTimeSeconds": 1.656999945640564
        }, {
            "name": "T120.dat",
            "score": 201051137.2503662,
            "imageID": 0,
            "executionTimeSeconds": 1.6510000228881836
        }, 
        {
            "name": "T294.dat",
            "score": 201053615.51123428,
            "imageID": 0,
            "executionTimeSeconds": 1.6549999713897705
        }, {
            "name": "T200.dat",
            "score": 201526796.70174408,
            "imageID": 0,
            "executionTimeSeconds": 1.656999945640564
        }, {
            "name": "T150.dat",
            "score": 201626959.8862381,
            "imageID": 0,
            "executionTimeSeconds": 1.6549999713897705
        }, {
            "name": "T41.dat",
            "score": 202000003.84135437,
            "imageID": 0,
            "executionTimeSeconds": 1.6579999923706055
        }, {
            "name": "T52.dat",
            "score": 202088043.15224457,
            "imageID": 0,
            "executionTimeSeconds": 1.659999966621399
        }, {
            "name": "T141.dat",
            "score": 202168778.07624817,
            "imageID": 0,
            "executionTimeSeconds": 1.656000018119812
        }, {
            "name": "T280.dat",
            "score": 202717435.44330597,
            "imageID": 0,
            "executionTimeSeconds": 1.6629999876022339
        }, {
            "name": "T359.dat",
            "score": 202760991.9470749,
            "imageID": 0,
            "executionTimeSeconds": 1.656999945640564
        }, {
            "name": "T43.dat",
            "score": 203218142.65468597,
            "imageID": 0,
            "executionTimeSeconds": 1.6469999551773071
        }, {
            "name": "T130.dat",
            "score": 203816316.24121094,
            "imageID": 0,
            "executionTimeSeconds": 1.6519999504089355
        }, 
        {
            "name": "T156.dat",
            "score": 204260542.92028046,
            "imageID": 0,
            "executionTimeSeconds": 1.6670000553131104
        }, {
            "name": "T259.dat",
            "score": 205083249.92998505,
            "imageID": 0,
            "executionTimeSeconds": 1.6610000133514404
        }, {
            "name": "T109.dat",
            "score": 205105738.27289963,
            "imageID": 0,
            "executionTimeSeconds": 1.659000039100647
        }, {
            "name": "T206.dat",
            "score": 205859289.2541046,
            "imageID": 0,
            "executionTimeSeconds": 6.870999813079834
        }, {
            "name": "T189.dat",
            "score": 207363373.47574615,
            "imageID": 0,
            "executionTimeSeconds": 1.6679999828338623
        }, {
            "name": "T135.dat",
            "score": 207381147.5475235,
            "imageID": 0,
            "executionTimeSeconds": 1.6710000038146973
        }, {
            "name": "T229.dat",
            "score": 208400483.81549072,
            "imageID": 0,
            "executionTimeSeconds": 1.6610000133514404
        }, {
            "name": "T350.dat",
            "score": 209321145.97659302,
            "imageID": 0,
            "executionTimeSeconds": 1.402999997138977
        }, {
            "name": "T322.dat",
            "score": 209731366.22155762,
            "imageID": 0,
            "executionTimeSeconds": 1.6549999713897705
        }, {
            "name": "T333.dat",
            "score": 211476299.00291443,
            "imageID": 0,
            "executionTimeSeconds": 1.6610000133514404
        }, 
        {
            "name": "T118.dat",
            "score": 212618554.286808,
            "imageID": 0,
            "executionTimeSeconds": 1.6610000133514404
        }, {
            "name": "T28.dat",
            "score": 212674898.1424942,
            "imageID": 0,
            "executionTimeSeconds": 1.6540000438690186
        }, {
            "name": "T363.dat",
            "score": 213540105.61886597,
            "imageID": 0,
            "executionTimeSeconds": 1.6579999923706055
        }, {
            "name": "T74.dat",
            "score": 214561395.6804123,
            "imageID": 0,
            "executionTimeSeconds": 1.652999997138977
        }, {
            "name": "T49.dat",
            "score": 214860472.9054947,
            "imageID": 0,
            "executionTimeSeconds": 1.6579999923706055
        }, {
            "name": "T7.dat",
            "score": 215598496.24440765,
            "imageID": 0,
            "executionTimeSeconds": 1.6629999876022339
        }, {
            "name": "T158.dat",
            "score": 217386437.8368225,
            "imageID": 0,
            "executionTimeSeconds": 1.6720000505447388
        }, {
            "name": "T295.dat",
            "score": 217956255.6086502,
            "imageID": 0,
            "executionTimeSeconds": 1.656000018119812
        }, {
            "name": "T44.dat",
            "score": 218151094.5226822,
            "imageID": 0,
            "executionTimeSeconds": 1.6619999408721924
        }, {
            "name": "T244.dat",
            "score": 218325601.01011658,
            "imageID": 0,
            "executionTimeSeconds": 1.065999984741211
        }, 
        {
            "name": "T266.dat",
            "score": 218715072.80976105,
            "imageID": 0,
            "executionTimeSeconds": 1.656000018119812
        }, {
            "name": "T300.dat",
            "score": 218922880.02095795,
            "imageID": 0,
            "executionTimeSeconds": 1.6510000228881836
        }, {
            "name": "T188.dat",
            "score": 219017182.72365952,
            "imageID": 0,
            "executionTimeSeconds": 1.6629999876022339
        }, {
            "name": "T173.dat",
            "score": 219117819.45993042,
            "imageID": 0,
            "executionTimeSeconds": 1.6510000228881836
        }, {
            "name": "T352.dat",
            "score": 219906308.12954712,
            "imageID": 0,
            "executionTimeSeconds": 1.1490000486373901
        }, {
            "name": "T381.dat",
            "score": 222209599.99712372,
            "imageID": 0,
            "executionTimeSeconds": 1.659999966621399
        }, {
            "name": "T284.dat",
            "score": 222625306.96649933,
            "imageID": 0,
            "executionTimeSeconds": 1.659999966621399
        }, {
            "name": "T45.dat",
            "score": 223857249.39348602,
            "imageID": 0,
            "executionTimeSeconds": 1.6579999923706055
        }, {
            "name": "T315.dat",
            "score": 224135775.3052864,
            "imageID": 0,
            "executionTimeSeconds": 1.649999976158142
        }, {
            "name": "T335.dat",
            "score": 226891541.13851166,
            "imageID": 0,
            "executionTimeSeconds": 1.6649999618530273
        }, 
        {
            "name": "T367.dat",
            "score": 227524695.30303192,
            "imageID": 0,
            "executionTimeSeconds": 1.6519999504089355
        }, {
            "name": "T321.dat",
            "score": 228104075.553833,
            "imageID": 0,
            "executionTimeSeconds": 1.656999945640564
        }, {
            "name": "T348.dat",
            "score": 228152945.54373932,
            "imageID": 0,
            "executionTimeSeconds": 1.5809999704360962
        }, {
            "name": "T369.dat",
            "score": 229307301.62766647,
            "imageID": 0,
            "executionTimeSeconds": 0.23999999463558197
        }, {
            "name": "T23.dat",
            "score": 232155882.0666275,
            "imageID": 0,
            "executionTimeSeconds": 0.6909999847412109
        }, {
            "name": "T17.dat",
            "score": 233505466.8701439,
            "imageID": 0,
            "executionTimeSeconds": 0.4869999885559082
        }, {
            "name": "T299.dat",
            "score": 234800412.7287674,
            "imageID": 0,
            "executionTimeSeconds": 1.6549999713897705
        }, {
            "name": "T353.dat",
            "score": 235161232.4817276,
            "imageID": 0,
            "executionTimeSeconds": 1.6549999713897705
        }, {
            "name": "T382.dat",
            "score": 235643098.9293394,
            "imageID": 0,
            "executionTimeSeconds": 1.659999966621399
        }, {
            "name": "T132.dat",
            "score": 235655714.1085434,
            "imageID": 0,
            "executionTimeSeconds": 1.6549999713897705
        }, 
        {
            "name": "T337.dat",
            "score": 236139445.85668182,
            "imageID": 0,
            "executionTimeSeconds": 1.6480000019073486
        }, {
            "name": "T18.dat",
            "score": 236294807.7730484,
            "imageID": 0,
            "executionTimeSeconds": 1.6770000457763672
        }, {
            "name": "T22.dat",
            "score": 237305057.12908936,
            "imageID": 0,
            "executionTimeSeconds": 1.6660000085830688
        }, {
            "name": "T24.dat",
            "score": 237368978.31528854,
            "imageID": 0,
            "executionTimeSeconds": 0.6639999747276306
        }, {
            "name": "T19.dat",
            "score": 238376179.63130188,
            "imageID": 0,
            "executionTimeSeconds": 1.1109999418258667
        }, {
            "name": "T297.dat",
            "score": 245194719.37332916,
            "imageID": 0,
            "executionTimeSeconds": 1.6629999876022339
        }, {
            "name": "T296.dat",
            "score": 246293270.35716248,
            "imageID": 0,
            "executionTimeSeconds": 1.659999966621399
        }, {
            "name": "T346.dat",
            "score": 247147727.9901886,
            "imageID": 0,
            "executionTimeSeconds": 1.656999945640564
        }, {
            "name": "T323.dat",
            "score": 248611420.49700546,
            "imageID": 0,
            "executionTimeSeconds": 1.6579999923706055
        }, {
            "name": "T383.dat",
            "score": 249232304.02124023,
            "imageID": 0,
            "executionTimeSeconds": 1.652999997138977
        }, 
        {
            "name": "T377.dat",
            "score": 250873969.81415558,
            "imageID": 0,
            "executionTimeSeconds": 1.6540000438690186
        }, {
            "name": "T336.dat",
            "score": 250925243.98757172,
            "imageID": 0,
            "executionTimeSeconds": 1.6519999504089355
        }, {
            "name": "T375.dat",
            "score": 255440537.3362503,
            "imageID": 0,
            "executionTimeSeconds": 1.652999997138977
        }, {
            "name": "T356.dat",
            "score": 259601838.09355164,
            "imageID": 0,
            "executionTimeSeconds": 1.1770000457763672
        }, {
            "name": "T340.dat",
            "score": 263223555.926239,
            "imageID": 0,
            "executionTimeSeconds": 1.034000039100647
        }, {
            "name": "T332.dat",
            "score": 271961461.02116394,
            "imageID": 0,
            "executionTimeSeconds": 1.6610000133514404
        }, {
            "name": "T368.dat",
            "score": 283725964.21261597,
            "imageID": 0,
            "executionTimeSeconds": 0.953000009059906
        }, {
            "name": "T67.dat",
            "score": 284126576.66300964,
            "imageID": 0,
            "executionTimeSeconds": 1.656000018119812
        }, {
            "name": "T374.dat",
            "score": 289260497.02027893,
            "imageID": 0,
            "executionTimeSeconds": 1.6670000553131104
        }, {
            "name": "T380.dat",
            "score": 309741263.240345,
            "imageID": 0,
            "executionTimeSeconds": 1.6610000133514404
        }, 
        {
            "name": "T378.dat",
            "score": 313716818.6991348,
            "imageID": 0,
            "executionTimeSeconds": 1.6720000505447388
        }, {
            "name": "T373.dat",
            "score": 318830261.23364496,
            "imageID": 0,
            "executionTimeSeconds": 1.6549999713897705
        }, {
            "name": "T379.dat",
            "score": 322131197.21362495,
            "imageID": 0,
            "executionTimeSeconds": 1.3380000591278076
        }
    ]
}