{
    "version": "v6",
    "resultCount": 383,
    "queryArea": 16348.905086409584,
    "buildinfo": {
        "commit": "fbac0bf7a7a6915955230908b68d0d070141a0ed",
        "commit_author": "bartvbl",
        "commit_date": "2021-03-02 18:02:19 +0100"
    },
    "results": [
        {
            "name": "T4.dat",
            "score": 25291834.62802124,
            "imageID": 0,
            "executionTimeSeconds": 2.065000057220459
        }, {
            "name": "T10.dat",
            "score": 28613490.15612793,
            "imageID": 0,
            "executionTimeSeconds": 0.5249999761581421
        }, {
            "name": "T328.dat",
            "score": 29558941.602294922,
            "imageID": 0,
            "executionTimeSeconds": 0.5289999842643738
        }, {
            "name": "T96.dat",
            "score": 29662468.937286377,
            "imageID": 0,
            "executionTimeSeconds": 2.056999921798706
        }, {
            "name": "T131.dat",
            "score": 29677893.63293457,
            "imageID": 0,
            "executionTimeSeconds": 0.5239999890327454
        }, {
            "name": "T149.dat",
            "score": 29782220.936157227,
            "imageID": 0,
            "executionTimeSeconds": 2.0789999961853027
        }, {
            "name": "T119.dat",
            "score": 30637678.573257446,
            "imageID": 0,
            "executionTimeSeconds": 0.5230000019073486
        }, {
            "name": "T42.dat",
            "score": 30644520.592178345,
            "imageID": 0,
            "executionTimeSeconds": 0.5289999842643738
        }, {
            "name": "T262.dat",
            "score": 30907271.222976685,
            "imageID": 0,
            "executionTimeSeconds": 0.5249999761581421
        }, {
            "name": "T165.dat",
            "score": 32132298.362342834,
            "imageID": 0,
            "executionTimeSeconds": 0.5220000147819519
        }, 
        {
            "name": "T318.dat",
            "score": 32234488.470108032,
            "imageID": 0,
            "executionTimeSeconds": 0.5249999761581421
        }, {
            "name": "T168.dat",
            "score": 33037308.886047363,
            "imageID": 0,
            "executionTimeSeconds": 0.5260000228881836
        }, {
            "name": "T138.dat",
            "score": 33047456.93988037,
            "imageID": 0,
            "executionTimeSeconds": 0.5220000147819519
        }, {
            "name": "T187.dat",
            "score": 33384192.202774048,
            "imageID": 0,
            "executionTimeSeconds": 0.5270000100135803
        }, {
            "name": "T237.dat",
            "score": 34673947.50621033,
            "imageID": 0,
            "executionTimeSeconds": 0.527999997138977
        }, {
            "name": "T185.dat",
            "score": 34783704.38952637,
            "imageID": 0,
            "executionTimeSeconds": 1.0379999876022339
        }, {
            "name": "T175.dat",
            "score": 35848377.060920715,
            "imageID": 0,
            "executionTimeSeconds": 2.0810000896453857
        }, {
            "name": "T301.dat",
            "score": 36031546.43965149,
            "imageID": 0,
            "executionTimeSeconds": 0.5289999842643738
        }, {
            "name": "T113.dat",
            "score": 36084963.68850708,
            "imageID": 0,
            "executionTimeSeconds": 0.5249999761581421
        }, {
            "name": "T150.dat",
            "score": 36128386.2149353,
            "imageID": 0,
            "executionTimeSeconds": 0.5260000228881836
        }, 
        {
            "name": "T37.dat",
            "score": 36393257.10055542,
            "imageID": 0,
            "executionTimeSeconds": 2.068000078201294
        }, {
            "name": "T192.dat",
            "score": 36496144.56652832,
            "imageID": 0,
            "executionTimeSeconds": 2.069000005722046
        }, {
            "name": "T232.dat",
            "score": 36601178.9717865,
            "imageID": 0,
            "executionTimeSeconds": 0.5239999890327454
        }, {
            "name": "T311.dat",
            "score": 36640793.915252686,
            "imageID": 0,
            "executionTimeSeconds": 0.5299999713897705
        }, {
            "name": "T50.dat",
            "score": 37396334.20599365,
            "imageID": 0,
            "executionTimeSeconds": 2.071000099182129
        }, {
            "name": "T228.dat",
            "score": 37651237.9964447,
            "imageID": 0,
            "executionTimeSeconds": 0.531000018119812
        }, {
            "name": "T130.dat",
            "score": 37793497.9936142,
            "imageID": 0,
            "executionTimeSeconds": 0.5239999890327454
        }, {
            "name": "T196.dat",
            "score": 37961243.23432922,
            "imageID": 0,
            "executionTimeSeconds": 0.5270000100135803
        }, {
            "name": "T256.dat",
            "score": 38210799.392822266,
            "imageID": 0,
            "executionTimeSeconds": 0.5260000228881836
        }, {
            "name": "T184.dat",
            "score": 38237271.91964722,
            "imageID": 0,
            "executionTimeSeconds": 0.5329999923706055
        }, 
        {
            "name": "T317.dat",
            "score": 38314996.81297302,
            "imageID": 0,
            "executionTimeSeconds": 0.527999997138977
        }, {
            "name": "T327.dat",
            "score": 38399294.68043518,
            "imageID": 0,
            "executionTimeSeconds": 0.5260000228881836
        }, {
            "name": "T82.dat",
            "score": 38430889.75726318,
            "imageID": 0,
            "executionTimeSeconds": 0.531000018119812
        }, {
            "name": "T364.dat",
            "score": 38742224.786735535,
            "imageID": 0,
            "executionTimeSeconds": 0.527999997138977
        }, {
            "name": "T110.dat",
            "score": 38755205.003837585,
            "imageID": 0,
            "executionTimeSeconds": 2.072000026702881
        }, {
            "name": "T357.dat",
            "score": 38807908.062942505,
            "imageID": 0,
            "executionTimeSeconds": 0.5230000019073486
        }, {
            "name": "T278.dat",
            "score": 39236248.69859314,
            "imageID": 0,
            "executionTimeSeconds": 0.5289999842643738
        }, {
            "name": "T109.dat",
            "score": 39455697.62327576,
            "imageID": 0,
            "executionTimeSeconds": 0.5230000019073486
        }, {
            "name": "T106.dat",
            "score": 39487158.9500885,
            "imageID": 0,
            "executionTimeSeconds": 0.5270000100135803
        }, {
            "name": "T43.dat",
            "score": 39548563.02183533,
            "imageID": 0,
            "executionTimeSeconds": 0.5180000066757202
        }, 
        {
            "name": "T294.dat",
            "score": 39564071.93486023,
            "imageID": 0,
            "executionTimeSeconds": 0.5260000228881836
        }, {
            "name": "T215.dat",
            "score": 39610637.284347534,
            "imageID": 0,
            "executionTimeSeconds": 0.5220000147819519
        }, {
            "name": "T220.dat",
            "score": 39717032.612335205,
            "imageID": 0,
            "executionTimeSeconds": 0.5189999938011169
        }, {
            "name": "T140.dat",
            "score": 39923862.53681946,
            "imageID": 0,
            "executionTimeSeconds": 0.531000018119812
        }, {
            "name": "T363.dat",
            "score": 39953535.75289917,
            "imageID": 0,
            "executionTimeSeconds": 0.5239999890327454
        }, {
            "name": "T111.dat",
            "score": 40004841.87956238,
            "imageID": 0,
            "executionTimeSeconds": 0.5270000100135803
        }, {
            "name": "T265.dat",
            "score": 40177295.773254395,
            "imageID": 0,
            "executionTimeSeconds": 0.5249999761581421
        }, {
            "name": "T52.dat",
            "score": 40177576.74166107,
            "imageID": 0,
            "executionTimeSeconds": 0.5260000228881836
        }, {
            "name": "T56.dat",
            "score": 40212111.097976685,
            "imageID": 0,
            "executionTimeSeconds": 2.066999912261963
        }, {
            "name": "T360.dat",
            "score": 40242204.202819824,
            "imageID": 0,
            "executionTimeSeconds": 0.5239999890327454
        }, 
        {
            "name": "T98.dat",
            "score": 40283121.50241089,
            "imageID": 0,
            "executionTimeSeconds": 0.5270000100135803
        }, {
            "name": "T90.dat",
            "score": 40405094.73536682,
            "imageID": 0,
            "executionTimeSeconds": 0.5260000228881836
        }, {
            "name": "T248.dat",
            "score": 40418426.63661194,
            "imageID": 0,
            "executionTimeSeconds": 0.5230000019073486
        }, {
            "name": "T100.dat",
            "score": 40537719.24467468,
            "imageID": 0,
            "executionTimeSeconds": 0.5220000147819519
        }, {
            "name": "T2.dat",
            "score": 40551592.4667511,
            "imageID": 0,
            "executionTimeSeconds": 0.5270000100135803
        }, {
            "name": "T333.dat",
            "score": 40731362.23287964,
            "imageID": 0,
            "executionTimeSeconds": 0.5270000100135803
        }, {
            "name": "T250.dat",
            "score": 40996764.56767273,
            "imageID": 0,
            "executionTimeSeconds": 2.062999963760376
        }, {
            "name": "T197.dat",
            "score": 41081664.51551819,
            "imageID": 0,
            "executionTimeSeconds": 2.062999963760376
        }, {
            "name": "T72.dat",
            "score": 41134388.77433014,
            "imageID": 0,
            "executionTimeSeconds": 0.5239999890327454
        }, {
            "name": "T54.dat",
            "score": 41148700.38781738,
            "imageID": 0,
            "executionTimeSeconds": 2.071000099182129
        }, 
        {
            "name": "T351.dat",
            "score": 41538150.14767456,
            "imageID": 0,
            "executionTimeSeconds": 0.5270000100135803
        }, {
            "name": "T147.dat",
            "score": 41693613.96533203,
            "imageID": 0,
            "executionTimeSeconds": 0.5230000019073486
        }, {
            "name": "T303.dat",
            "score": 41763988.339019775,
            "imageID": 0,
            "executionTimeSeconds": 0.5239999890327454
        }, {
            "name": "T195.dat",
            "score": 41799216.4752121,
            "imageID": 0,
            "executionTimeSeconds": 0.527999997138977
        }, {
            "name": "T200.dat",
            "score": 41835052.698280334,
            "imageID": 0,
            "executionTimeSeconds": 0.5239999890327454
        }, {
            "name": "T38.dat",
            "score": 42084548.30809021,
            "imageID": 0,
            "executionTimeSeconds": 0.5260000228881836
        }, {
            "name": "T214.dat",
            "score": 42291805.84877014,
            "imageID": 0,
            "executionTimeSeconds": 0.5230000019073486
        }, {
            "name": "T116.dat",
            "score": 42332854.06072998,
            "imageID": 0,
            "executionTimeSeconds": 2.0820000171661377
        }, {
            "name": "T53.dat",
            "score": 42338152.4831543,
            "imageID": 0,
            "executionTimeSeconds": 2.063999891281128
        }, {
            "name": "T103.dat",
            "score": 42511573.85972595,
            "imageID": 0,
            "executionTimeSeconds": 0.5220000147819519
        }, 
        {
            "name": "T135.dat",
            "score": 42801510.93571472,
            "imageID": 0,
            "executionTimeSeconds": 0.5370000004768372
        }, {
            "name": "T89.dat",
            "score": 42854691.76423645,
            "imageID": 0,
            "executionTimeSeconds": 0.5270000100135803
        }, {
            "name": "T255.dat",
            "score": 43099261.45187378,
            "imageID": 0,
            "executionTimeSeconds": 0.5270000100135803
        }, {
            "name": "T156.dat",
            "score": 43157936.05850983,
            "imageID": 0,
            "executionTimeSeconds": 0.5239999890327454
        }, {
            "name": "T46.dat",
            "score": 43362349.010635376,
            "imageID": 0,
            "executionTimeSeconds": 0.5249999761581421
        }, {
            "name": "T280.dat",
            "score": 43383903.40068054,
            "imageID": 0,
            "executionTimeSeconds": 0.527999997138977
        }, {
            "name": "T370.dat",
            "score": 43389423.693984985,
            "imageID": 0,
            "executionTimeSeconds": 0.5249999761581421
        }, {
            "name": "T172.dat",
            "score": 43480426.64605713,
            "imageID": 0,
            "executionTimeSeconds": 0.5220000147819519
        }, {
            "name": "T371.dat",
            "score": 43538435.94831085,
            "imageID": 0,
            "executionTimeSeconds": 0.5260000228881836
        }, {
            "name": "T241.dat",
            "score": 43700297.249557495,
            "imageID": 0,
            "executionTimeSeconds": 0.5260000228881836
        }, 
        {
            "name": "T366.dat",
            "score": 43792806.866744995,
            "imageID": 0,
            "executionTimeSeconds": 0.5299999713897705
        }, {
            "name": "T354.dat",
            "score": 43982094.226486206,
            "imageID": 0,
            "executionTimeSeconds": 0.5249999761581421
        }, {
            "name": "T292.dat",
            "score": 43990785.43086243,
            "imageID": 0,
            "executionTimeSeconds": 0.5270000100135803
        }, {
            "name": "T97.dat",
            "score": 44138070.76559448,
            "imageID": 0,
            "executionTimeSeconds": 0.527999997138977
        }, {
            "name": "T49.dat",
            "score": 44320826.790267944,
            "imageID": 0,
            "executionTimeSeconds": 0.5220000147819519
        }, {
            "name": "T80.dat",
            "score": 44365903.40573883,
            "imageID": 0,
            "executionTimeSeconds": 0.5249999761581421
        }, {
            "name": "T108.dat",
            "score": 44442683.84881592,
            "imageID": 0,
            "executionTimeSeconds": 2.069000005722046
        }, {
            "name": "T316.dat",
            "score": 44465370.45599365,
            "imageID": 0,
            "executionTimeSeconds": 0.5210000276565552
        }, {
            "name": "T270.dat",
            "score": 44466496.064712524,
            "imageID": 0,
            "executionTimeSeconds": 0.5210000276565552
        }, {
            "name": "T246.dat",
            "score": 44476176.6164093,
            "imageID": 0,
            "executionTimeSeconds": 0.527999997138977
        }, 
        {
            "name": "T331.dat",
            "score": 44490780.45397949,
            "imageID": 0,
            "executionTimeSeconds": 0.527999997138977
        }, {
            "name": "T141.dat",
            "score": 44499014.66306305,
            "imageID": 0,
            "executionTimeSeconds": 0.527999997138977
        }, {
            "name": "T219.dat",
            "score": 44618392.0068512,
            "imageID": 0,
            "executionTimeSeconds": 0.5360000133514404
        }, {
            "name": "T3.dat",
            "score": 44634099.44900513,
            "imageID": 0,
            "executionTimeSeconds": 0.5299999713897705
        }, {
            "name": "T221.dat",
            "score": 44767276.45487976,
            "imageID": 0,
            "executionTimeSeconds": 0.5299999713897705
        }, {
            "name": "T55.dat",
            "score": 44817909.966056824,
            "imageID": 0,
            "executionTimeSeconds": 2.052000045776367
        }, {
            "name": "T322.dat",
            "score": 44828148.767204285,
            "imageID": 0,
            "executionTimeSeconds": 0.5199999809265137
        }, {
            "name": "T189.dat",
            "score": 44943918.696372986,
            "imageID": 0,
            "executionTimeSeconds": 0.5249999761581421
        }, {
            "name": "T242.dat",
            "score": 45030579.01522827,
            "imageID": 0,
            "executionTimeSeconds": 0.5299999713897705
        }, {
            "name": "T205.dat",
            "score": 45066892.069869995,
            "imageID": 0,
            "executionTimeSeconds": 0.5260000228881836
        }, 
        {
            "name": "T266.dat",
            "score": 45138853.53791809,
            "imageID": 0,
            "executionTimeSeconds": 0.5270000100135803
        }, {
            "name": "T124.dat",
            "score": 45231961.93333435,
            "imageID": 0,
            "executionTimeSeconds": 0.5249999761581421
        }, {
            "name": "T102.dat",
            "score": 45271251.6472168,
            "imageID": 0,
            "executionTimeSeconds": 0.5230000019073486
        }, {
            "name": "T359.dat",
            "score": 45312528.34220886,
            "imageID": 0,
            "executionTimeSeconds": 0.5239999890327454
        }, {
            "name": "T41.dat",
            "score": 45497090.039886475,
            "imageID": 0,
            "executionTimeSeconds": 0.5249999761581421
        }, {
            "name": "T190.dat",
            "score": 45509428.509132385,
            "imageID": 0,
            "executionTimeSeconds": 0.5220000147819519
        }, {
            "name": "T26.dat",
            "score": 45665032.068733215,
            "imageID": 0,
            "executionTimeSeconds": 0.531000018119812
        }, {
            "name": "T13.dat",
            "score": 45676046.18145752,
            "imageID": 0,
            "executionTimeSeconds": 2.062999963760376
        }, {
            "name": "T216.dat",
            "score": 45900635.55835724,
            "imageID": 0,
            "executionTimeSeconds": 0.5230000019073486
        }, {
            "name": "T152.dat",
            "score": 45961816.07095337,
            "imageID": 0,
            "executionTimeSeconds": 0.5220000147819519
        }, 
        {
            "name": "T259.dat",
            "score": 45987713.18022919,
            "imageID": 0,
            "executionTimeSeconds": 0.5239999890327454
        }, {
            "name": "T188.dat",
            "score": 45996209.850624084,
            "imageID": 0,
            "executionTimeSeconds": 0.5260000228881836
        }, {
            "name": "T276.dat",
            "score": 46069639.16117096,
            "imageID": 0,
            "executionTimeSeconds": 0.5249999761581421
        }, {
            "name": "T275.dat",
            "score": 46079347.5168457,
            "imageID": 0,
            "executionTimeSeconds": 0.5289999842643738
        }, {
            "name": "T217.dat",
            "score": 46080432.16378784,
            "imageID": 0,
            "executionTimeSeconds": 0.5260000228881836
        }, {
            "name": "T74.dat",
            "score": 46103719.26222229,
            "imageID": 0,
            "executionTimeSeconds": 0.5249999761581421
        }, {
            "name": "T334.dat",
            "score": 46131927.967536926,
            "imageID": 0,
            "executionTimeSeconds": 0.5289999842643738
        }, {
            "name": "T182.dat",
            "score": 46169252.93386841,
            "imageID": 0,
            "executionTimeSeconds": 0.5220000147819519
        }, {
            "name": "T180.dat",
            "score": 46229169.323913574,
            "imageID": 0,
            "executionTimeSeconds": 0.527999997138977
        }, {
            "name": "T33.dat",
            "score": 46279490.2157135,
            "imageID": 0,
            "executionTimeSeconds": 0.5260000228881836
        }, 
        {
            "name": "T223.dat",
            "score": 46506255.002471924,
            "imageID": 0,
            "executionTimeSeconds": 0.5230000019073486
        }, {
            "name": "T252.dat",
            "score": 46595475.91506958,
            "imageID": 0,
            "executionTimeSeconds": 0.5299999713897705
        }, {
            "name": "T112.dat",
            "score": 46618942.8395462,
            "imageID": 0,
            "executionTimeSeconds": 2.062000036239624
        }, {
            "name": "T11.dat",
            "score": 46720053.48617554,
            "imageID": 0,
            "executionTimeSeconds": 0.5249999761581421
        }, {
            "name": "T61.dat",
            "score": 46790439.95552826,
            "imageID": 0,
            "executionTimeSeconds": 0.5289999842643738
        }, {
            "name": "T314.dat",
            "score": 47053206.25289917,
            "imageID": 0,
            "executionTimeSeconds": 0.5249999761581421
        }, {
            "name": "T198.dat",
            "score": 47214862.8085022,
            "imageID": 0,
            "executionTimeSeconds": 0.5239999890327454
        }, {
            "name": "T208.dat",
            "score": 47218100.579956055,
            "imageID": 0,
            "executionTimeSeconds": 0.5239999890327454
        }, {
            "name": "T269.dat",
            "score": 47225614.71447754,
            "imageID": 0,
            "executionTimeSeconds": 0.5199999809265137
        }, {
            "name": "T94.dat",
            "score": 47253839.93499756,
            "imageID": 0,
            "executionTimeSeconds": 0.5230000019073486
        }, 
        {
            "name": "T85.dat",
            "score": 47307775.43017578,
            "imageID": 0,
            "executionTimeSeconds": 0.5289999842643738
        }, {
            "name": "T240.dat",
            "score": 47323463.43682861,
            "imageID": 0,
            "executionTimeSeconds": 0.5230000019073486
        }, {
            "name": "T69.dat",
            "score": 47373640.004486084,
            "imageID": 0,
            "executionTimeSeconds": 0.527999997138977
        }, {
            "name": "T86.dat",
            "score": 47449385.859176636,
            "imageID": 0,
            "executionTimeSeconds": 2.071000099182129
        }, {
            "name": "T186.dat",
            "score": 47473401.12617493,
            "imageID": 0,
            "executionTimeSeconds": 0.5260000228881836
        }, {
            "name": "T204.dat",
            "score": 47501654.88232422,
            "imageID": 0,
            "executionTimeSeconds": 0.5260000228881836
        }, {
            "name": "T376.dat",
            "score": 47574481.00770569,
            "imageID": 0,
            "executionTimeSeconds": 0.5239999890327454
        }, {
            "name": "T148.dat",
            "score": 47591126.3602829,
            "imageID": 0,
            "executionTimeSeconds": 2.065999984741211
        }, {
            "name": "T47.dat",
            "score": 47745350.72759247,
            "imageID": 0,
            "executionTimeSeconds": 0.5199999809265137
        }, {
            "name": "T233.dat",
            "score": 47833290.21095276,
            "imageID": 0,
            "executionTimeSeconds": 0.5339999794960022
        }, 
        {
            "name": "T171.dat",
            "score": 47855597.82260132,
            "imageID": 0,
            "executionTimeSeconds": 0.5230000019073486
        }, {
            "name": "T279.dat",
            "score": 47936136.01850891,
            "imageID": 0,
            "executionTimeSeconds": 0.5249999761581421
        }, {
            "name": "T32.dat",
            "score": 48008244.364715576,
            "imageID": 0,
            "executionTimeSeconds": 0.5210000276565552
        }, {
            "name": "T1.dat",
            "score": 48133010.70614624,
            "imageID": 0,
            "executionTimeSeconds": 0.5220000147819519
        }, {
            "name": "T312.dat",
            "score": 48191431.99316406,
            "imageID": 0,
            "executionTimeSeconds": 0.5260000228881836
        }, {
            "name": "T169.dat",
            "score": 48247634.77168274,
            "imageID": 0,
            "executionTimeSeconds": 0.5289999842643738
        }, {
            "name": "T173.dat",
            "score": 48262737.825737,
            "imageID": 0,
            "executionTimeSeconds": 0.5249999761581421
        }, {
            "name": "T194.dat",
            "score": 48263685.91635132,
            "imageID": 0,
            "executionTimeSeconds": 0.5230000019073486
        }, {
            "name": "T133.dat",
            "score": 48301086.87225342,
            "imageID": 0,
            "executionTimeSeconds": 0.5320000052452087
        }, {
            "name": "T193.dat",
            "score": 48318325.716033936,
            "imageID": 0,
            "executionTimeSeconds": 0.5220000147819519
        }, 
        {
            "name": "T105.dat",
            "score": 48321294.68595886,
            "imageID": 0,
            "executionTimeSeconds": 0.5260000228881836
        }, {
            "name": "T78.dat",
            "score": 48339258.95366669,
            "imageID": 0,
            "executionTimeSeconds": 0.5239999890327454
        }, {
            "name": "T326.dat",
            "score": 48356185.73120117,
            "imageID": 0,
            "executionTimeSeconds": 0.5270000100135803
        }, {
            "name": "T358.dat",
            "score": 48475504.90112305,
            "imageID": 0,
            "executionTimeSeconds": 0.5289999842643738
        }, {
            "name": "T295.dat",
            "score": 48478037.96778107,
            "imageID": 0,
            "executionTimeSeconds": 0.527999997138977
        }, {
            "name": "T227.dat",
            "score": 48677236.184028625,
            "imageID": 0,
            "executionTimeSeconds": 0.5289999842643738
        }, {
            "name": "T253.dat",
            "score": 48765585.71888733,
            "imageID": 0,
            "executionTimeSeconds": 2.0759999752044678
        }, {
            "name": "T350.dat",
            "score": 48770170.37050629,
            "imageID": 0,
            "executionTimeSeconds": 0.4410000145435333
        }, {
            "name": "T104.dat",
            "score": 48857815.57079315,
            "imageID": 0,
            "executionTimeSeconds": 0.5210000276565552
        }, {
            "name": "T222.dat",
            "score": 48900360.94857788,
            "imageID": 0,
            "executionTimeSeconds": 0.5180000066757202
        }, 
        {
            "name": "T249.dat",
            "score": 48933804.167526245,
            "imageID": 0,
            "executionTimeSeconds": 0.5289999842643738
        }, {
            "name": "T281.dat",
            "score": 48953897.11062622,
            "imageID": 0,
            "executionTimeSeconds": 0.5249999761581421
        }, {
            "name": "T66.dat",
            "score": 48985743.29804993,
            "imageID": 0,
            "executionTimeSeconds": 0.5260000228881836
        }, {
            "name": "T320.dat",
            "score": 48998930.7288208,
            "imageID": 0,
            "executionTimeSeconds": 2.063999891281128
        }, {
            "name": "T329.dat",
            "score": 49009893.72647095,
            "imageID": 0,
            "executionTimeSeconds": 0.5289999842643738
        }, {
            "name": "T9.dat",
            "score": 49044224.746902466,
            "imageID": 0,
            "executionTimeSeconds": 0.527999997138977
        }, {
            "name": "T21.dat",
            "score": 49103518.974487305,
            "imageID": 0,
            "executionTimeSeconds": 0.5270000100135803
        }, {
            "name": "T158.dat",
            "score": 49135618.06782532,
            "imageID": 0,
            "executionTimeSeconds": 0.527999997138977
        }, {
            "name": "T12.dat",
            "score": 49140684.632873535,
            "imageID": 0,
            "executionTimeSeconds": 0.5199999809265137
        }, {
            "name": "T226.dat",
            "score": 49166692.20036316,
            "imageID": 0,
            "executionTimeSeconds": 0.5230000019073486
        }, 
        {
            "name": "T25.dat",
            "score": 49299228.92240143,
            "imageID": 0,
            "executionTimeSeconds": 0.5270000100135803
        }, {
            "name": "T273.dat",
            "score": 49321265.347328186,
            "imageID": 0,
            "executionTimeSeconds": 0.5270000100135803
        }, {
            "name": "T29.dat",
            "score": 49462049.17542267,
            "imageID": 0,
            "executionTimeSeconds": 0.5329999923706055
        }, {
            "name": "T151.dat",
            "score": 49498820.76347351,
            "imageID": 0,
            "executionTimeSeconds": 0.5270000100135803
        }, {
            "name": "T178.dat",
            "score": 49691015.169036865,
            "imageID": 0,
            "executionTimeSeconds": 0.5329999923706055
        }, {
            "name": "T5.dat",
            "score": 49708241.962387085,
            "imageID": 0,
            "executionTimeSeconds": 0.5299999713897705
        }, {
            "name": "T199.dat",
            "score": 49767056.42160034,
            "imageID": 0,
            "executionTimeSeconds": 0.5210000276565552
        }, {
            "name": "T126.dat",
            "score": 49789283.01407623,
            "imageID": 0,
            "executionTimeSeconds": 0.5230000019073486
        }, {
            "name": "T15.dat",
            "score": 49804182.50959778,
            "imageID": 0,
            "executionTimeSeconds": 0.5230000019073486
        }, {
            "name": "T264.dat",
            "score": 49885862.190216064,
            "imageID": 0,
            "executionTimeSeconds": 0.5210000276565552
        }, 
        {
            "name": "T381.dat",
            "score": 49902781.96268463,
            "imageID": 0,
            "executionTimeSeconds": 0.5230000019073486
        }, {
            "name": "T28.dat",
            "score": 49976454.06783295,
            "imageID": 0,
            "executionTimeSeconds": 0.5230000019073486
        }, {
            "name": "T206.dat",
            "score": 50002634.91634369,
            "imageID": 0,
            "executionTimeSeconds": 2.0899999141693115
        }, {
            "name": "T122.dat",
            "score": 50006797.58761597,
            "imageID": 0,
            "executionTimeSeconds": 0.5230000019073486
        }, {
            "name": "T128.dat",
            "score": 50053825.562316895,
            "imageID": 0,
            "executionTimeSeconds": 0.5270000100135803
        }, {
            "name": "T95.dat",
            "score": 50075713.299957275,
            "imageID": 0,
            "executionTimeSeconds": 0.5220000147819519
        }, {
            "name": "T154.dat",
            "score": 50080810.35600281,
            "imageID": 0,
            "executionTimeSeconds": 0.5260000228881836
        }, {
            "name": "T68.dat",
            "score": 50137324.982543945,
            "imageID": 0,
            "executionTimeSeconds": 0.5239999890327454
        }, {
            "name": "T134.dat",
            "score": 50348227.93838501,
            "imageID": 0,
            "executionTimeSeconds": 0.5220000147819519
        }, {
            "name": "T338.dat",
            "score": 50371105.73728943,
            "imageID": 0,
            "executionTimeSeconds": 0.5230000019073486
        }, 
        {
            "name": "T267.dat",
            "score": 50383316.34512329,
            "imageID": 0,
            "executionTimeSeconds": 0.5350000262260437
        }, {
            "name": "T75.dat",
            "score": 50397342.764411926,
            "imageID": 0,
            "executionTimeSeconds": 2.069000005722046
        }, {
            "name": "T144.dat",
            "score": 50461383.706474304,
            "imageID": 0,
            "executionTimeSeconds": 2.053999900817871
        }, {
            "name": "T125.dat",
            "score": 50492489.11967468,
            "imageID": 0,
            "executionTimeSeconds": 0.5189999938011169
        }, {
            "name": "T174.dat",
            "score": 50555846.87205505,
            "imageID": 0,
            "executionTimeSeconds": 0.527999997138977
        }, {
            "name": "T218.dat",
            "score": 50626764.32993317,
            "imageID": 0,
            "executionTimeSeconds": 0.5270000100135803
        }, {
            "name": "T62.dat",
            "score": 50644632.837394714,
            "imageID": 0,
            "executionTimeSeconds": 2.069999933242798
        }, {
            "name": "T203.dat",
            "score": 50742179.988464355,
            "imageID": 0,
            "executionTimeSeconds": 0.5239999890327454
        }, {
            "name": "T123.dat",
            "score": 50789560.50782776,
            "imageID": 0,
            "executionTimeSeconds": 0.5220000147819519
        }, {
            "name": "T87.dat",
            "score": 50893929.8986969,
            "imageID": 0,
            "executionTimeSeconds": 0.527999997138977
        }, 
        {
            "name": "T236.dat",
            "score": 50934766.39928436,
            "imageID": 0,
            "executionTimeSeconds": 0.5239999890327454
        }, {
            "name": "T159.dat",
            "score": 50975526.36834717,
            "imageID": 0,
            "executionTimeSeconds": 0.5339999794960022
        }, {
            "name": "T287.dat",
            "score": 50997273.742752075,
            "imageID": 0,
            "executionTimeSeconds": 0.5249999761581421
        }, {
            "name": "T101.dat",
            "score": 51041072.97250748,
            "imageID": 0,
            "executionTimeSeconds": 2.053999900817871
        }, {
            "name": "T99.dat",
            "score": 51041792.89116669,
            "imageID": 0,
            "executionTimeSeconds": 0.5220000147819519
        }, {
            "name": "T235.dat",
            "score": 51045943.06967163,
            "imageID": 0,
            "executionTimeSeconds": 0.5320000052452087
        }, {
            "name": "T298.dat",
            "score": 51151345.94577026,
            "imageID": 0,
            "executionTimeSeconds": 0.527999997138977
        }, {
            "name": "T145.dat",
            "score": 51195595.8057251,
            "imageID": 0,
            "executionTimeSeconds": 2.0510001182556152
        }, {
            "name": "T88.dat",
            "score": 51322523.20837402,
            "imageID": 0,
            "executionTimeSeconds": 0.5320000052452087
        }, {
            "name": "T48.dat",
            "score": 51355233.37147522,
            "imageID": 0,
            "executionTimeSeconds": 0.5230000019073486
        }, 
        {
            "name": "T284.dat",
            "score": 51387847.11672974,
            "imageID": 0,
            "executionTimeSeconds": 0.5260000228881836
        }, {
            "name": "T57.dat",
            "score": 51405264.0843811,
            "imageID": 0,
            "executionTimeSeconds": 0.5260000228881836
        }, {
            "name": "T176.dat",
            "score": 51419023.081352234,
            "imageID": 0,
            "executionTimeSeconds": 0.5270000100135803
        }, {
            "name": "T207.dat",
            "score": 51443053.338394165,
            "imageID": 0,
            "executionTimeSeconds": 0.5270000100135803
        }, {
            "name": "T247.dat",
            "score": 51456184.483551025,
            "imageID": 0,
            "executionTimeSeconds": 0.531000018119812
        }, {
            "name": "T285.dat",
            "score": 51514045.68926239,
            "imageID": 0,
            "executionTimeSeconds": 2.068000078201294
        }, {
            "name": "T244.dat",
            "score": 51562708.24152374,
            "imageID": 0,
            "executionTimeSeconds": 0.335999995470047
        }, {
            "name": "T91.dat",
            "score": 51620319.5736084,
            "imageID": 0,
            "executionTimeSeconds": 0.5199999809265137
        }, {
            "name": "T347.dat",
            "score": 51643434.39639282,
            "imageID": 0,
            "executionTimeSeconds": 0.5230000019073486
        }, {
            "name": "T229.dat",
            "score": 51697079.829071045,
            "imageID": 0,
            "executionTimeSeconds": 0.5270000100135803
        }, 
        {
            "name": "T302.dat",
            "score": 51758127.1696167,
            "imageID": 0,
            "executionTimeSeconds": 0.5370000004768372
        }, {
            "name": "T343.dat",
            "score": 51967170.38278198,
            "imageID": 0,
            "executionTimeSeconds": 0.5270000100135803
        }, {
            "name": "T251.dat",
            "score": 52036676.29774475,
            "imageID": 0,
            "executionTimeSeconds": 0.5260000228881836
        }, {
            "name": "T143.dat",
            "score": 52037151.60677338,
            "imageID": 0,
            "executionTimeSeconds": 0.5260000228881836
        }, {
            "name": "T341.dat",
            "score": 52074488.635261536,
            "imageID": 0,
            "executionTimeSeconds": 0.5289999842643738
        }, {
            "name": "T70.dat",
            "score": 52110199.234954834,
            "imageID": 0,
            "executionTimeSeconds": 0.5270000100135803
        }, {
            "name": "T114.dat",
            "score": 52175829.73188782,
            "imageID": 0,
            "executionTimeSeconds": 0.5270000100135803
        }, {
            "name": "T51.dat",
            "score": 52271619.62944031,
            "imageID": 0,
            "executionTimeSeconds": 2.065000057220459
        }, {
            "name": "T58.dat",
            "score": 52298900.77429199,
            "imageID": 0,
            "executionTimeSeconds": 2.068000078201294
        }, {
            "name": "T254.dat",
            "score": 52317156.280570984,
            "imageID": 0,
            "executionTimeSeconds": 0.5289999842643738
        }, 
        {
            "name": "T177.dat",
            "score": 52488026.70489502,
            "imageID": 0,
            "executionTimeSeconds": 0.5260000228881836
        }, {
            "name": "T231.dat",
            "score": 52585350.04736328,
            "imageID": 0,
            "executionTimeSeconds": 0.5239999890327454
        }, {
            "name": "T44.dat",
            "score": 52594907.76034546,
            "imageID": 0,
            "executionTimeSeconds": 0.5249999761581421
        }, {
            "name": "T245.dat",
            "score": 52633704.99581909,
            "imageID": 0,
            "executionTimeSeconds": 0.5220000147819519
        }, {
            "name": "T260.dat",
            "score": 52660737.16074371,
            "imageID": 0,
            "executionTimeSeconds": 0.5230000019073486
        }, {
            "name": "T45.dat",
            "score": 52702711.331329346,
            "imageID": 0,
            "executionTimeSeconds": 0.5230000019073486
        }, {
            "name": "T137.dat",
            "score": 52731361.69391632,
            "imageID": 0,
            "executionTimeSeconds": 0.527999997138977
        }, {
            "name": "T179.dat",
            "score": 52758731.86000061,
            "imageID": 0,
            "executionTimeSeconds": 0.527999997138977
        }, {
            "name": "T139.dat",
            "score": 52786134.52182007,
            "imageID": 0,
            "executionTimeSeconds": 0.527999997138977
        }, {
            "name": "T191.dat",
            "score": 52848759.85513306,
            "imageID": 0,
            "executionTimeSeconds": 0.5199999809265137
        }, 
        {
            "name": "T8.dat",
            "score": 52855373.91168213,
            "imageID": 0,
            "executionTimeSeconds": 0.531000018119812
        }, {
            "name": "T153.dat",
            "score": 52865162.31278992,
            "imageID": 0,
            "executionTimeSeconds": 0.5249999761581421
        }, {
            "name": "T288.dat",
            "score": 52904751.1494751,
            "imageID": 0,
            "executionTimeSeconds": 0.5199999809265137
        }, {
            "name": "T342.dat",
            "score": 52908250.38771057,
            "imageID": 0,
            "executionTimeSeconds": 0.5289999842643738
        }, {
            "name": "T372.dat",
            "score": 52914348.31896973,
            "imageID": 0,
            "executionTimeSeconds": 0.527999997138977
        }, {
            "name": "T59.dat",
            "score": 52917481.803756714,
            "imageID": 0,
            "executionTimeSeconds": 2.069000005722046
        }, {
            "name": "T136.dat",
            "score": 53063967.47099304,
            "imageID": 0,
            "executionTimeSeconds": 0.5289999842643738
        }, {
            "name": "T60.dat",
            "score": 53263510.394355774,
            "imageID": 0,
            "executionTimeSeconds": 2.069000005722046
        }, {
            "name": "T31.dat",
            "score": 53274156.28085327,
            "imageID": 0,
            "executionTimeSeconds": 0.5230000019073486
        }, {
            "name": "T201.dat",
            "score": 53276005.3297348,
            "imageID": 0,
            "executionTimeSeconds": 0.5299999713897705
        }, 
        {
            "name": "T161.dat",
            "score": 53298585.88785553,
            "imageID": 0,
            "executionTimeSeconds": 0.5230000019073486
        }, {
            "name": "T313.dat",
            "score": 53299596.49240112,
            "imageID": 0,
            "executionTimeSeconds": 0.5239999890327454
        }, {
            "name": "T348.dat",
            "score": 53416429.401916504,
            "imageID": 0,
            "executionTimeSeconds": 0.5019999742507935
        }, {
            "name": "T76.dat",
            "score": 53418836.58973694,
            "imageID": 0,
            "executionTimeSeconds": 0.5299999713897705
        }, {
            "name": "T34.dat",
            "score": 53428376.02154541,
            "imageID": 0,
            "executionTimeSeconds": 0.5220000147819519
        }, {
            "name": "T117.dat",
            "score": 53455424.7594223,
            "imageID": 0,
            "executionTimeSeconds": 0.527999997138977
        }, {
            "name": "T271.dat",
            "score": 53456961.40917969,
            "imageID": 0,
            "executionTimeSeconds": 0.5260000228881836
        }, {
            "name": "T162.dat",
            "score": 53490330.87678528,
            "imageID": 0,
            "executionTimeSeconds": 0.5220000147819519
        }, {
            "name": "T170.dat",
            "score": 53510968.51689148,
            "imageID": 0,
            "executionTimeSeconds": 0.527999997138977
        }, {
            "name": "T330.dat",
            "score": 53512518.87266922,
            "imageID": 0,
            "executionTimeSeconds": 2.063999891281128
        }, 
        {
            "name": "T183.dat",
            "score": 53535466.650405884,
            "imageID": 0,
            "executionTimeSeconds": 0.5249999761581421
        }, {
            "name": "T283.dat",
            "score": 53728979.16998291,
            "imageID": 0,
            "executionTimeSeconds": 0.527999997138977
        }, {
            "name": "T84.dat",
            "score": 53756068.934402466,
            "imageID": 0,
            "executionTimeSeconds": 0.5270000100135803
        }, {
            "name": "T146.dat",
            "score": 53809593.83168793,
            "imageID": 0,
            "executionTimeSeconds": 0.5220000147819519
        }, {
            "name": "T164.dat",
            "score": 53892026.02497101,
            "imageID": 0,
            "executionTimeSeconds": 0.5299999713897705
        }, {
            "name": "T300.dat",
            "score": 54033954.32989502,
            "imageID": 0,
            "executionTimeSeconds": 0.5260000228881836
        }, {
            "name": "T291.dat",
            "score": 54045121.72966766,
            "imageID": 0,
            "executionTimeSeconds": 0.5289999842643738
        }, {
            "name": "T129.dat",
            "score": 54064961.160736084,
            "imageID": 0,
            "executionTimeSeconds": 0.5220000147819519
        }, {
            "name": "T308.dat",
            "score": 54067890.149902344,
            "imageID": 0,
            "executionTimeSeconds": 0.5189999938011169
        }, {
            "name": "T339.dat",
            "score": 54184400.177978516,
            "imageID": 0,
            "executionTimeSeconds": 0.5260000228881836
        }, 
        {
            "name": "T163.dat",
            "score": 54190739.2461853,
            "imageID": 0,
            "executionTimeSeconds": 0.5270000100135803
        }, {
            "name": "T335.dat",
            "score": 54285189.4990387,
            "imageID": 0,
            "executionTimeSeconds": 0.5260000228881836
        }, {
            "name": "T115.dat",
            "score": 54336428.99659729,
            "imageID": 0,
            "executionTimeSeconds": 0.5270000100135803
        }, {
            "name": "T289.dat",
            "score": 54414777.48527527,
            "imageID": 0,
            "executionTimeSeconds": 0.527999997138977
        }, {
            "name": "T40.dat",
            "score": 54436510.757247925,
            "imageID": 0,
            "executionTimeSeconds": 0.5230000019073486
        }, {
            "name": "T355.dat",
            "score": 54507978.783065796,
            "imageID": 0,
            "executionTimeSeconds": 0.5299999713897705
        }, {
            "name": "T155.dat",
            "score": 54601376.131095886,
            "imageID": 0,
            "executionTimeSeconds": 0.5260000228881836
        }, {
            "name": "T210.dat",
            "score": 54685288.01150513,
            "imageID": 0,
            "executionTimeSeconds": 0.5210000276565552
        }, {
            "name": "T272.dat",
            "score": 54816206.344436646,
            "imageID": 0,
            "executionTimeSeconds": 2.069999933242798
        }, {
            "name": "T238.dat",
            "score": 54914756.74571228,
            "imageID": 0,
            "executionTimeSeconds": 0.5270000100135803
        }, 
        {
            "name": "T225.dat",
            "score": 54942009.97214508,
            "imageID": 0,
            "executionTimeSeconds": 0.5289999842643738
        }, {
            "name": "T27.dat",
            "score": 54973293.061416626,
            "imageID": 0,
            "executionTimeSeconds": 0.5249999761581421
        }, {
            "name": "T213.dat",
            "score": 55050256.4621582,
            "imageID": 0,
            "executionTimeSeconds": 0.5220000147819519
        }, {
            "name": "T277.dat",
            "score": 55137945.16455078,
            "imageID": 0,
            "executionTimeSeconds": 0.5249999761581421
        }, {
            "name": "T367.dat",
            "score": 55186202.068351746,
            "imageID": 0,
            "executionTimeSeconds": 0.5220000147819519
        }, {
            "name": "T64.dat",
            "score": 55211296.122039795,
            "imageID": 0,
            "executionTimeSeconds": 0.5249999761581421
        }, {
            "name": "T321.dat",
            "score": 55252460.76257324,
            "imageID": 0,
            "executionTimeSeconds": 0.5270000100135803
        }, {
            "name": "T7.dat",
            "score": 55332080.401519775,
            "imageID": 0,
            "executionTimeSeconds": 0.5260000228881836
        }, {
            "name": "T306.dat",
            "score": 55519078.562698364,
            "imageID": 0,
            "executionTimeSeconds": 0.5320000052452087
        }, {
            "name": "T16.dat",
            "score": 55738360.348236084,
            "imageID": 0,
            "executionTimeSeconds": 0.5210000276565552
        }, 
        {
            "name": "T352.dat",
            "score": 55878723.76741791,
            "imageID": 0,
            "executionTimeSeconds": 0.3619999885559082
        }, {
            "name": "T35.dat",
            "score": 55954158.87385559,
            "imageID": 0,
            "executionTimeSeconds": 0.5299999713897705
        }, {
            "name": "T305.dat",
            "score": 55959482.5612793,
            "imageID": 0,
            "executionTimeSeconds": 0.5289999842643738
        }, {
            "name": "T349.dat",
            "score": 56041031.31738281,
            "imageID": 0,
            "executionTimeSeconds": 0.5299999713897705
        }, {
            "name": "T65.dat",
            "score": 56073291.03619385,
            "imageID": 0,
            "executionTimeSeconds": 0.5239999890327454
        }, {
            "name": "T230.dat",
            "score": 56126198.93179321,
            "imageID": 0,
            "executionTimeSeconds": 0.527999997138977
        }, {
            "name": "T345.dat",
            "score": 56129605.220184326,
            "imageID": 0,
            "executionTimeSeconds": 0.5339999794960022
        }, {
            "name": "T73.dat",
            "score": 56203792.735198975,
            "imageID": 0,
            "executionTimeSeconds": 0.5260000228881836
        }, {
            "name": "T77.dat",
            "score": 56293445.582855225,
            "imageID": 0,
            "executionTimeSeconds": 0.5230000019073486
        }, {
            "name": "T81.dat",
            "score": 56366142.08097839,
            "imageID": 0,
            "executionTimeSeconds": 0.5270000100135803
        }, 
        {
            "name": "T344.dat",
            "score": 56420686.45401001,
            "imageID": 0,
            "executionTimeSeconds": 0.5239999890327454
        }, {
            "name": "T268.dat",
            "score": 56426426.44718933,
            "imageID": 0,
            "executionTimeSeconds": 0.5289999842643738
        }, {
            "name": "T310.dat",
            "score": 56508542.87827301,
            "imageID": 0,
            "executionTimeSeconds": 0.5270000100135803
        }, {
            "name": "T362.dat",
            "score": 56508542.87827301,
            "imageID": 0,
            "executionTimeSeconds": 0.5249999761581421
        }, {
            "name": "T36.dat",
            "score": 56569652.14520264,
            "imageID": 0,
            "executionTimeSeconds": 0.5210000276565552
        }, {
            "name": "T6.dat",
            "score": 56596644.704330444,
            "imageID": 0,
            "executionTimeSeconds": 0.5249999761581421
        }, {
            "name": "T257.dat",
            "score": 56633301.267333984,
            "imageID": 0,
            "executionTimeSeconds": 0.5230000019073486
        }, {
            "name": "T325.dat",
            "score": 56664299.54321289,
            "imageID": 0,
            "executionTimeSeconds": 0.5249999761581421
        }, {
            "name": "T261.dat",
            "score": 56684733.070510864,
            "imageID": 0,
            "executionTimeSeconds": 0.5360000133514404
        }, {
            "name": "T304.dat",
            "score": 56736573.91188812,
            "imageID": 0,
            "executionTimeSeconds": 0.5289999842643738
        }, 
        {
            "name": "T20.dat",
            "score": 56739444.59606171,
            "imageID": 0,
            "executionTimeSeconds": 0.531000018119812
        }, {
            "name": "T212.dat",
            "score": 56789023.71871948,
            "imageID": 0,
            "executionTimeSeconds": 0.5239999890327454
        }, {
            "name": "T361.dat",
            "score": 56797331.43949127,
            "imageID": 0,
            "executionTimeSeconds": 0.5230000019073486
        }, {
            "name": "T107.dat",
            "score": 57089266.41143799,
            "imageID": 0,
            "executionTimeSeconds": 0.5210000276565552
        }, {
            "name": "T211.dat",
            "score": 57365173.818481445,
            "imageID": 0,
            "executionTimeSeconds": 0.5289999842643738
        }, {
            "name": "T319.dat",
            "score": 57425934.7375412,
            "imageID": 0,
            "executionTimeSeconds": 0.5289999842643738
        }, {
            "name": "T83.dat",
            "score": 57448742.7220459,
            "imageID": 0,
            "executionTimeSeconds": 0.5339999794960022
        }, {
            "name": "T157.dat",
            "score": 57457021.72137451,
            "imageID": 0,
            "executionTimeSeconds": 0.5230000019073486
        }, {
            "name": "T337.dat",
            "score": 57502940.0390625,
            "imageID": 0,
            "executionTimeSeconds": 0.5249999761581421
        }, {
            "name": "T258.dat",
            "score": 57521709.92392731,
            "imageID": 0,
            "executionTimeSeconds": 0.5289999842643738
        }, 
        {
            "name": "T234.dat",
            "score": 58285484.19371033,
            "imageID": 0,
            "executionTimeSeconds": 0.5249999761581421
        }, {
            "name": "T282.dat",
            "score": 58532289.40246582,
            "imageID": 0,
            "executionTimeSeconds": 0.5249999761581421
        }, {
            "name": "T286.dat",
            "score": 58598322.01457214,
            "imageID": 0,
            "executionTimeSeconds": 0.5389999747276306
        }, {
            "name": "T315.dat",
            "score": 58626406.85972595,
            "imageID": 0,
            "executionTimeSeconds": 0.5249999761581421
        }, {
            "name": "T166.dat",
            "score": 58645849.55218506,
            "imageID": 0,
            "executionTimeSeconds": 0.5289999842643738
        }, {
            "name": "T14.dat",
            "score": 58979822.92858887,
            "imageID": 0,
            "executionTimeSeconds": 0.5239999890327454
        }, {
            "name": "T353.dat",
            "score": 59163388.50680542,
            "imageID": 0,
            "executionTimeSeconds": 0.5220000147819519
        }, {
            "name": "T127.dat",
            "score": 59375484.25691986,
            "imageID": 0,
            "executionTimeSeconds": 0.5239999890327454
        }, {
            "name": "T30.dat",
            "score": 59473184.38090515,
            "imageID": 0,
            "executionTimeSeconds": 0.5249999761581421
        }, {
            "name": "T79.dat",
            "score": 59487561.22628784,
            "imageID": 0,
            "executionTimeSeconds": 0.5289999842643738
        }, 
        {
            "name": "T382.dat",
            "score": 59704638.13794327,
            "imageID": 0,
            "executionTimeSeconds": 0.531000018119812
        }, {
            "name": "T132.dat",
            "score": 59764360.15911865,
            "imageID": 0,
            "executionTimeSeconds": 0.5230000019073486
        }, {
            "name": "T307.dat",
            "score": 59769828.1947937,
            "imageID": 0,
            "executionTimeSeconds": 0.5260000228881836
        }, {
            "name": "T160.dat",
            "score": 59833634.92086792,
            "imageID": 0,
            "executionTimeSeconds": 0.5170000195503235
        }, {
            "name": "T71.dat",
            "score": 59954756.41934204,
            "imageID": 0,
            "executionTimeSeconds": 0.5270000100135803
        }, {
            "name": "T39.dat",
            "score": 59986180.545928955,
            "imageID": 0,
            "executionTimeSeconds": 0.5270000100135803
        }, {
            "name": "T181.dat",
            "score": 60066769.80477905,
            "imageID": 0,
            "executionTimeSeconds": 0.5230000019073486
        }, {
            "name": "T167.dat",
            "score": 60199481.976501465,
            "imageID": 0,
            "executionTimeSeconds": 0.5220000147819519
        }, {
            "name": "T63.dat",
            "score": 60299493.79512024,
            "imageID": 0,
            "executionTimeSeconds": 0.5260000228881836
        }, {
            "name": "T293.dat",
            "score": 60707574.542144775,
            "imageID": 0,
            "executionTimeSeconds": 0.5270000100135803
        }, 
        {
            "name": "T202.dat",
            "score": 60794622.11140442,
            "imageID": 0,
            "executionTimeSeconds": 0.5230000019073486
        }, {
            "name": "T263.dat",
            "score": 60850552.13056946,
            "imageID": 0,
            "executionTimeSeconds": 0.5249999761581421
        }, {
            "name": "T243.dat",
            "score": 61089478.779174805,
            "imageID": 0,
            "executionTimeSeconds": 0.5329999923706055
        }, {
            "name": "T365.dat",
            "score": 61271183.33560181,
            "imageID": 0,
            "executionTimeSeconds": 0.5289999842643738
        }, {
            "name": "T224.dat",
            "score": 61284791.37937927,
            "imageID": 0,
            "executionTimeSeconds": 0.5120000243186951
        }, {
            "name": "T299.dat",
            "score": 61460867.00022888,
            "imageID": 0,
            "executionTimeSeconds": 0.5249999761581421
        }, {
            "name": "T142.dat",
            "score": 61502011.38423157,
            "imageID": 0,
            "executionTimeSeconds": 0.527999997138977
        }, {
            "name": "T290.dat",
            "score": 61558298.061294556,
            "imageID": 0,
            "executionTimeSeconds": 0.5170000195503235
        }, {
            "name": "T209.dat",
            "score": 62036794.524627686,
            "imageID": 0,
            "executionTimeSeconds": 0.5239999890327454
        }, {
            "name": "T309.dat",
            "score": 62090030.96556091,
            "imageID": 0,
            "executionTimeSeconds": 0.5260000228881836
        }, 
        {
            "name": "T92.dat",
            "score": 62447081.41598511,
            "imageID": 0,
            "executionTimeSeconds": 0.5239999890327454
        }, {
            "name": "T377.dat",
            "score": 63330628.10383606,
            "imageID": 0,
            "executionTimeSeconds": 0.5220000147819519
        }, {
            "name": "T239.dat",
            "score": 63899193.85131836,
            "imageID": 0,
            "executionTimeSeconds": 2.066999912261963
        }, {
            "name": "T296.dat",
            "score": 64438451.294677734,
            "imageID": 0,
            "executionTimeSeconds": 0.5230000019073486
        }, {
            "name": "T297.dat",
            "score": 64784055.02119446,
            "imageID": 0,
            "executionTimeSeconds": 0.5260000228881836
        }, {
            "name": "T274.dat",
            "score": 64981895.20146179,
            "imageID": 0,
            "executionTimeSeconds": 0.531000018119812
        }, {
            "name": "T346.dat",
            "score": 65177966.07077026,
            "imageID": 0,
            "executionTimeSeconds": 0.5260000228881836
        }, {
            "name": "T323.dat",
            "score": 65318590.250572205,
            "imageID": 0,
            "executionTimeSeconds": 0.5230000019073486
        }, {
            "name": "T23.dat",
            "score": 65344966.5010376,
            "imageID": 0,
            "executionTimeSeconds": 0.2160000056028366
        }, {
            "name": "T336.dat",
            "score": 65420843.82367706,
            "imageID": 0,
            "executionTimeSeconds": 0.5270000100135803
        }, 
        {
            "name": "T121.dat",
            "score": 65644523.878082275,
            "imageID": 0,
            "executionTimeSeconds": 0.5289999842643738
        }, {
            "name": "T17.dat",
            "score": 66755663.7935791,
            "imageID": 0,
            "executionTimeSeconds": 0.14800000190734863
        }, {
            "name": "T93.dat",
            "score": 67262045.49240112,
            "imageID": 0,
            "executionTimeSeconds": 0.5249999761581421
        }, {
            "name": "T369.dat",
            "score": 67337367.72769165,
            "imageID": 0,
            "executionTimeSeconds": 0.0729999989271164
        }, {
            "name": "T19.dat",
            "score": 67561606.86151123,
            "imageID": 0,
            "executionTimeSeconds": 0.3499999940395355
        }, {
            "name": "T383.dat",
            "score": 68411838.74101257,
            "imageID": 0,
            "executionTimeSeconds": 0.5189999938011169
        }, {
            "name": "T24.dat",
            "score": 68962979.2185669,
            "imageID": 0,
            "executionTimeSeconds": 0.20600000023841858
        }, {
            "name": "T22.dat",
            "score": 68978376.375,
            "imageID": 0,
            "executionTimeSeconds": 0.527999997138977
        }, {
            "name": "T340.dat",
            "score": 69589628.04608154,
            "imageID": 0,
            "executionTimeSeconds": 0.3269999921321869
        }, {
            "name": "T356.dat",
            "score": 69659329.4967041,
            "imageID": 0,
            "executionTimeSeconds": 0.3720000088214874
        }, 
        {
            "name": "T324.dat",
            "score": 69668540.99789429,
            "imageID": 0,
            "executionTimeSeconds": 0.5270000100135803
        }, {
            "name": "T18.dat",
            "score": 70147191.28196716,
            "imageID": 0,
            "executionTimeSeconds": 0.5299999713897705
        }, {
            "name": "T120.dat",
            "score": 70312573.471344,
            "imageID": 0,
            "executionTimeSeconds": 0.5220000147819519
        }, {
            "name": "T375.dat",
            "score": 71776009.26263428,
            "imageID": 0,
            "executionTimeSeconds": 0.5220000147819519
        }, {
            "name": "T118.dat",
            "score": 73044752.66986084,
            "imageID": 0,
            "executionTimeSeconds": 0.5249999761581421
        }, {
            "name": "T332.dat",
            "score": 74395235.67922974,
            "imageID": 0,
            "executionTimeSeconds": 0.5249999761581421
        }, {
            "name": "T368.dat",
            "score": 78008704.91312408,
            "imageID": 0,
            "executionTimeSeconds": 0.29600000381469727
        }, {
            "name": "T67.dat",
            "score": 80514859.33532715,
            "imageID": 0,
            "executionTimeSeconds": 0.5270000100135803
        }, {
            "name": "T374.dat",
            "score": 82378923.3684082,
            "imageID": 0,
            "executionTimeSeconds": 0.5329999923706055
        }, {
            "name": "T380.dat",
            "score": 90675470.51837158,
            "imageID": 0,
            "executionTimeSeconds": 0.527999997138977
        }, 
        {
            "name": "T378.dat",
            "score": 92615307.71203613,
            "imageID": 0,
            "executionTimeSeconds": 0.5249999761581421
        }, {
            "name": "T373.dat",
            "score": 94620881.73754883,
            "imageID": 0,
            "executionTimeSeconds": 0.5270000100135803
        }, {
            "name": "T379.dat",
            "score": 95266490.60534668,
            "imageID": 0,
            "executionTimeSeconds": 0.421999990940094
        }
    ]
}